[{"step": 0, "t_elapsed": 1.0, "events": ["add_stream", "add_stream", "add_stream"], "observation": {"per_stream": {"0": {"fps_avg": 14.05, "infer_fps": 14.05, "latency_p95_ms": 228.79, "infer_latency_p95_ms": 228.79, "current_mode": "FULL", "detection_count_avg": 5.9, "frames_in_current_mode": 10, "frame_count": 10}, "1": {"fps_avg": 17.64, "infer_fps": 17.64, "latency_p95_ms": 284.15, "infer_latency_p95_ms": 284.15, "current_mode": "FULL", "detection_count_avg": 5.89, "frames_in_current_mode": 9, "frame_count": 9}, "2": {"fps_avg": 17.64, "infer_fps": 17.64, "latency_p95_ms": 263.67, "infer_latency_p95_ms": 263.67, "current_mode": "FULL", "detection_count_avg": 5.89, "frames_in_current_mode": 9, "frame_count": 9}}, "global": {"gpu_util_avg": 27.2, "n_active_streams": 3, "mem_used_mb": 5908.0, "n_streams_by_mode": {"FULL": 3, "LITE": 0, "SKIP": 0, "OFFLOAD": 0}}, "t_collect": 1773604574.3500674}, "action": null, "n_active": 3, "mode_counts": {"FULL": 3, "LITE": 0, "SKIP": 0, "OFFLOAD": 0}}, {"step": 1, "t_elapsed": 2.01, "events": [], "observation": {"per_stream": {"0": {"fps_avg": 16.36, "infer_fps": 16.36, "latency_p95_ms": 67.17, "infer_latency_p95_ms": 67.17, "current_mode": "FULL", "detection_count_avg": 6.13, "frames_in_current_mode": 15, "frame_count": 15}, "1": {"fps_avg": 16.36, "infer_fps": 16.36, "latency_p95_ms": 67.21, "infer_latency_p95_ms": 67.21, "current_mode": "FULL", "detection_count_avg": 6.13, "frames_in_current_mode": 15, "frame_count": 15}, "2": {"fps_avg": 16.36, "infer_fps": 16.36, "latency_p95_ms": 67.21, "infer_latency_p95_ms": 67.21, "current_mode": "FULL", "detection_count_avg": 6.13, "frames_in_current_mode": 15, "frame_count": 15}}, "global": {"gpu_util_avg": 72.6, "n_active_streams": 3, "mem_used_mb": 5922.0, "n_streams_by_mode": {"FULL": 3, "LITE": 0, "SKIP": 0, "OFFLOAD": 0}}, "t_collect": 1773604575.3541038}, "action": null, "n_active": 3, "mode_counts": {"FULL": 3, "LITE": 0, "SKIP": 0, "OFFLOAD": 0}}, {"step": 2, "t_elapsed": 3.01, "events": [], "observation": {"per_stream": {"0": {"fps_avg": 17.14, "infer_fps": 17.14, "latency_p95_ms": 66.79, "infer_latency_p95_ms": 66.79, "current_mode": "FULL", "detection_count_avg": 8.44, "frames_in_current_mode": 16, "frame_count": 16}, "1": {"fps_avg": 17.14, "infer_fps": 17.14, "latency_p95_ms": 66.76, "infer_latency_p95_ms": 66.76, "current_mode": "FULL", "detection_count_avg": 8.31, "frames_in_current_mode": 16, "frame_count": 16}, "2": {"fps_avg": 17.14, "infer_fps": 17.14, "latency_p95_ms": 66.79, "infer_latency_p95_ms": 66.79, "current_mode": "FULL", "detection_count_avg": 8.31, "frames_in_current_mode": 16, "frame_count": 16}}, "global": {"gpu_util_avg": 25.1, "n_active_streams": 3, "mem_used_mb": 5922.0, "n_streams_by_mode": {"FULL": 3, "LITE": 0, "SKIP": 0, "OFFLOAD": 0}}, "t_collect": 1773604576.358703}, "action": null, "n_active": 3, "mode_counts": {"FULL": 3, "LITE": 0, "SKIP": 0, "OFFLOAD": 0}}, {"step": 3, "t_elapsed": 4.02, "events": [], "observation": {"per_stream": {"0": {"fps_avg": 18.68, "infer_fps": 18.68, "latency_p95_ms": 60.04, "infer_latency_p95_ms": 60.04, "current_mode": "FULL", "detection_count_avg": 9.33, "frames_in_current_mode": 18, "frame_count": 18}, "1": {"fps_avg": 18.69, "infer_fps": 18.69, "latency_p95_ms": 59.87, "infer_latency_p95_ms": 59.87, "current_mode": "FULL", "detection_count_avg": 9.28, "frames_in_current_mode": 18, "frame_count": 18}, "2": {"fps_avg": 18.69, "infer_fps": 18.69, "latency_p95_ms": 59.89, "infer_latency_p95_ms": 59.89, "current_mode": "FULL", "detection_count_avg": 9.28, "frames_in_current_mode": 18, "frame_count": 18}}, "global": {"gpu_util_avg": 42.8, "n_active_streams": 3, "mem_used_mb": 5922.0, "n_streams_by_mode": {"FULL": 3, "LITE": 0, "SKIP": 0, "OFFLOAD": 0}}, "t_collect": 1773604577.3627117}, "action": null, "n_active": 3, "mode_counts": {"FULL": 3, "LITE": 0, "SKIP": 0, "OFFLOAD": 0}}, {"step": 4, "t_elapsed": 5.02, "events": [], "observation": {"per_stream": {"0": {"fps_avg": 19.11, "infer_fps": 19.11, "latency_p95_ms": 58.76, "infer_latency_p95_ms": 58.76, "current_mode": "FULL", "detection_count_avg": 7.12, "frames_in_current_mode": 16, "frame_count": 16}, "1": {"fps_avg": 19.11, "infer_fps": 19.11, "latency_p95_ms": 58.81, "infer_latency_p95_ms": 58.81, "current_mode": "FULL", "detection_count_avg": 7.25, "frames_in_current_mode": 16, "frame_count": 16}, "2": {"fps_avg": 19.11, "infer_fps": 19.11, "latency_p95_ms": 58.87, "infer_latency_p95_ms": 58.87, "current_mode": "FULL", "detection_count_avg": 7.25, "frames_in_current_mode": 16, "frame_count": 16}}, "global": {"gpu_util_avg": 62.7, "n_active_streams": 3, "mem_used_mb": 5922.0, "n_streams_by_mode": {"FULL": 3, "LITE": 0, "SKIP": 0, "OFFLOAD": 0}}, "t_collect": 1773604578.3666854}, "action": null, "n_active": 3, "mode_counts": {"FULL": 3, "LITE": 0, "SKIP": 0, "OFFLOAD": 0}}, {"step": 5, "t_elapsed": 6.03, "events": [], "observation": {"per_stream": {"0": {"fps_avg": 15.94, "infer_fps": 15.94, "latency_p95_ms": 140.16, "infer_latency_p95_ms": 140.16, "current_mode": "FULL", "detection_count_avg": 8.0, "frames_in_current_mode": 15, "frame_count": 15}, "1": {"fps_avg": 17.0, "infer_fps": 17.0, "latency_p95_ms": 102.46, "infer_latency_p95_ms": 102.46, "current_mode": "FULL", "detection_count_avg": 7.94, "frames_in_current_mode": 16, "frame_count": 16}, "2": {"fps_avg": 15.95, "infer_fps": 15.95, "latency_p95_ms": 170.55, "infer_latency_p95_ms": 170.55, "current_mode": "FULL", "detection_count_avg": 7.79, "frames_in_current_mode": 14, "frame_count": 14}}, "global": {"gpu_util_avg": 59.2, "n_active_streams": 3, "mem_used_mb": 5922.0, "n_streams_by_mode": {"FULL": 3, "LITE": 0, "SKIP": 0, "OFFLOAD": 0}}, "t_collect": 1773604579.3707604}, "action": null, "n_active": 3, "mode_counts": {"FULL": 3, "LITE": 0, "SKIP": 0, "OFFLOAD": 0}}, {"step": 6, "t_elapsed": 7.03, "events": [], "observation": {"per_stream": {"0": {"fps_avg": 18.83, "infer_fps": 18.83, "latency_p95_ms": 59.96, "infer_latency_p95_ms": 59.96, "current_mode": "FULL", "detection_count_avg": 8.29, "frames_in_current_mode": 17, "frame_count": 17}, "1": {"fps_avg": 18.82, "infer_fps": 18.82, "latency_p95_ms": 60.44, "infer_latency_p95_ms": 60.44, "current_mode": "FULL", "detection_count_avg": 8.29, "frames_in_current_mode": 17, "frame_count": 17}, "2": {"fps_avg": 18.82, "infer_fps": 18.82, "latency_p95_ms": 59.25, "infer_latency_p95_ms": 59.25, "current_mode": "FULL", "detection_count_avg": 8.29, "frames_in_current_mode": 17, "frame_count": 17}}, "global": {"gpu_util_avg": 33.8, "n_active_streams": 3, "mem_used_mb": 5923.0, "n_streams_by_mode": {"FULL": 3, "LITE": 0, "SKIP": 0, "OFFLOAD": 0}}, "t_collect": 1773604580.3770094}, "action": null, "n_active": 3, "mode_counts": {"FULL": 3, "LITE": 0, "SKIP": 0, "OFFLOAD": 0}}, {"step": 7, "t_elapsed": 8.04, "events": [], "observation": {"per_stream": {"0": {"fps_avg": 17.74, "infer_fps": 17.74, "latency_p95_ms": 69.04, "infer_latency_p95_ms": 69.04, "current_mode": "FULL", "detection_count_avg": 8.41, "frames_in_current_mode": 17, "frame_count": 17}, "1": {"fps_avg": 18.78, "infer_fps": 18.78, "latency_p95_ms": 59.71, "infer_latency_p95_ms": 59.71, "current_mode": "FULL", "detection_count_avg": 8.44, "frames_in_current_mode": 18, "frame_count": 18}, "2": {"fps_avg": 18.78, "infer_fps": 18.78, "latency_p95_ms": 59.69, "infer_latency_p95_ms": 59.69, "current_mode": "FULL", "detection_count_avg": 8.5, "frames_in_current_mode": 18, "frame_count": 18}}, "global": {"gpu_util_avg": 36.6, "n_active_streams": 3, "mem_used_mb": 5923.0, "n_streams_by_mode": {"FULL": 3, "LITE": 0, "SKIP": 0, "OFFLOAD": 0}}, "t_collect": 1773604581.3813236}, "action": null, "n_active": 3, "mode_counts": {"FULL": 3, "LITE": 0, "SKIP": 0, "OFFLOAD": 0}}, {"step": 8, "t_elapsed": 9.04, "events": [], "observation": {"per_stream": {"0": {"fps_avg": 18.83, "infer_fps": 18.83, "latency_p95_ms": 58.75, "infer_latency_p95_ms": 58.75, "current_mode": "FULL", "detection_count_avg": 9.94, "frames_in_current_mode": 18, "frame_count": 18}, "1": {"fps_avg": 18.83, "infer_fps": 18.83, "latency_p95_ms": 58.63, "infer_latency_p95_ms": 58.63, "current_mode": "FULL", "detection_count_avg": 9.94, "frames_in_current_mode": 18, "frame_count": 18}, "2": {"fps_avg": 18.83, "infer_fps": 18.83, "latency_p95_ms": 58.59, "infer_latency_p95_ms": 58.59, "current_mode": "FULL", "detection_count_avg": 9.89, "frames_in_current_mode": 18, "frame_count": 18}}, "global": {"gpu_util_avg": 72.6, "n_active_streams": 3, "mem_used_mb": 5923.0, "n_streams_by_mode": {"FULL": 3, "LITE": 0, "SKIP": 0, "OFFLOAD": 0}}, "t_collect": 1773604582.385396}, "action": null, "n_active": 3, "mode_counts": {"FULL": 3, "LITE": 0, "SKIP": 0, "OFFLOAD": 0}}, {"step": 9, "t_elapsed": 10.05, "events": [], "observation": {"per_stream": {"0": {"fps_avg": 18.75, "infer_fps": 18.75, "latency_p95_ms": 60.25, "infer_latency_p95_ms": 60.25, "current_mode": "FULL", "detection_count_avg": 9.11, "frames_in_current_mode": 18, "frame_count": 18}, "1": {"fps_avg": 18.74, "infer_fps": 18.74, "latency_p95_ms": 60.36, "infer_latency_p95_ms": 60.36, "current_mode": "FULL", "detection_count_avg": 9.11, "frames_in_current_mode": 18, "frame_count": 18}, "2": {"fps_avg": 18.79, "infer_fps": 18.79, "latency_p95_ms": 61.05, "infer_latency_p95_ms": 61.05, "current_mode": "FULL", "detection_count_avg": 9.11, "frames_in_current_mode": 18, "frame_count": 18}}, "global": {"gpu_util_avg": 83.6, "n_active_streams": 3, "mem_used_mb": 5921.0, "n_streams_by_mode": {"FULL": 3, "LITE": 0, "SKIP": 0, "OFFLOAD": 0}}, "t_collect": 1773604583.3898475}, "action": null, "n_active": 3, "mode_counts": {"FULL": 3, "LITE": 0, "SKIP": 0, "OFFLOAD": 0}}, {"step": 10, "t_elapsed": 11.05, "events": ["add_stream"], "observation": {"per_stream": {"0": {"fps_avg": 13.86, "infer_fps": 13.86, "latency_p95_ms": 129.97, "infer_latency_p95_ms": 129.97, "current_mode": "FULL", "detection_count_avg": 8.31, "frames_in_current_mode": 13, "frame_count": 13}, "1": {"fps_avg": 13.81, "infer_fps": 13.81, "latency_p95_ms": 130.66, "infer_latency_p95_ms": 130.66, "current_mode": "FULL", "detection_count_avg": 8.15, "frames_in_current_mode": 13, "frame_count": 13}, "2": {"fps_avg": 13.82, "infer_fps": 13.82, "latency_p95_ms": 129.23, "infer_latency_p95_ms": 129.23, "current_mode": "FULL", "detection_count_avg": 8.46, "frames_in_current_mode": 13, "frame_count": 13}, "3": {"fps_avg": 16.45, "infer_fps": 16.45, "latency_p95_ms": 182.67, "infer_latency_p95_ms": 182.67, "current_mode": "FULL", "detection_count_avg": 5.73, "frames_in_current_mode": 11, "frame_count": 11}}, "global": {"gpu_util_avg": 40.0, "n_active_streams": 4, "mem_used_mb": 5932.0, "n_streams_by_mode": {"FULL": 4, "LITE": 0, "SKIP": 0, "OFFLOAD": 0}}, "t_collect": 1773604584.397301}, "action": null, "n_active": 4, "mode_counts": {"FULL": 4, "LITE": 0, "SKIP": 0, "OFFLOAD": 0}}, {"step": 11, "t_elapsed": 12.06, "events": [], "observation": {"per_stream": {"0": {"fps_avg": 15.4, "infer_fps": 15.4, "latency_p95_ms": 90.33, "infer_latency_p95_ms": 90.33, "current_mode": "FULL", "detection_count_avg": 6.43, "frames_in_current_mode": 14, "frame_count": 14}, "1": {"fps_avg": 16.5, "infer_fps": 16.5, "latency_p95_ms": 70.41, "infer_latency_p95_ms": 70.41, "current_mode": "FULL", "detection_count_avg": 6.47, "frames_in_current_mode": 15, "frame_count": 15}, "2": {"fps_avg": 15.4, "infer_fps": 15.4, "latency_p95_ms": 89.22, "infer_latency_p95_ms": 89.22, "current_mode": "FULL", "detection_count_avg": 6.5, "frames_in_current_mode": 14, "frame_count": 14}, "3": {"fps_avg": 16.5, "infer_fps": 16.5, "latency_p95_ms": 70.8, "infer_latency_p95_ms": 70.8, "current_mode": "FULL", "detection_count_avg": 6.33, "frames_in_current_mode": 15, "frame_count": 15}}, "global": {"gpu_util_avg": 35.4, "n_active_streams": 4, "mem_used_mb": 5938.0, "n_streams_by_mode": {"FULL": 4, "LITE": 0, "SKIP": 0, "OFFLOAD": 0}}, "t_collect": 1773604585.404288}, "action": null, "n_active": 4, "mode_counts": {"FULL": 4, "LITE": 0, "SKIP": 0, "OFFLOAD": 0}}, {"step": 12, "t_elapsed": 13.07, "events": [], "observation": {"per_stream": {"0": {"fps_avg": 16.32, "infer_fps": 16.32, "latency_p95_ms": 70.24, "infer_latency_p95_ms": 70.24, "current_mode": "FULL", "detection_count_avg": 6.12, "frames_in_current_mode": 16, "frame_count": 16}, "1": {"fps_avg": 15.3, "infer_fps": 15.3, "latency_p95_ms": 89.07, "infer_latency_p95_ms": 89.07, "current_mode": "FULL", "detection_count_avg": 5.93, "frames_in_current_mode": 15, "frame_count": 15}, "2": {"fps_avg": 16.32, "infer_fps": 16.32, "latency_p95_ms": 70.31, "infer_latency_p95_ms": 70.31, "current_mode": "FULL", "detection_count_avg": 6.19, "frames_in_current_mode": 16, "frame_count": 16}, "3": {"fps_avg": 16.32, "infer_fps": 16.32, "latency_p95_ms": 70.21, "infer_latency_p95_ms": 70.21, "current_mode": "FULL", "detection_count_avg": 8.44, "frames_in_current_mode": 16, "frame_count": 16}}, "global": {"gpu_util_avg": 68.8, "n_active_streams": 4, "mem_used_mb": 5939.0, "n_streams_by_mode": {"FULL": 4, "LITE": 0, "SKIP": 0, "OFFLOAD": 0}}, "t_collect": 1773604586.4099016}, "action": null, "n_active": 4, "mode_counts": {"FULL": 4, "LITE": 0, "SKIP": 0, "OFFLOAD": 0}}, {"step": 13, "t_elapsed": 14.08, "events": [], "observation": {"per_stream": {"0": {"fps_avg": 15.8, "infer_fps": 15.8, "latency_p95_ms": 73.98, "infer_latency_p95_ms": 73.98, "current_mode": "FULL", "detection_count_avg": 4.29, "frames_in_current_mode": 14, "frame_count": 14}, "1": {"fps_avg": 15.8, "infer_fps": 15.8, "latency_p95_ms": 74.06, "infer_latency_p95_ms": 74.06, "current_mode": "FULL", "detection_count_avg": 4.21, "frames_in_current_mode": 14, "frame_count": 14}, "2": {"fps_avg": 15.8, "infer_fps": 15.8, "latency_p95_ms": 73.76, "infer_latency_p95_ms": 73.76, "current_mode": "FULL", "detection_count_avg": 4.36, "frames_in_current_mode": 14, "frame_count": 14}, "3": {"fps_avg": 15.8, "infer_fps": 15.8, "latency_p95_ms": 73.85, "infer_latency_p95_ms": 73.85, "current_mode": "FULL", "detection_count_avg": 9.43, "frames_in_current_mode": 14, "frame_count": 14}}, "global": {"gpu_util_avg": 48.4, "n_active_streams": 4, "mem_used_mb": 5941.0, "n_streams_by_mode": {"FULL": 4, "LITE": 0, "SKIP": 0, "OFFLOAD": 0}}, "t_collect": 1773604587.4177158}, "action": null, "n_active": 4, "mode_counts": {"FULL": 4, "LITE": 0, "SKIP": 0, "OFFLOAD": 0}}, {"step": 14, "t_elapsed": 15.08, "events": [], "observation": {"per_stream": {"0": {"fps_avg": 16.76, "infer_fps": 16.76, "latency_p95_ms": 69.77, "infer_latency_p95_ms": 69.77, "current_mode": "FULL", "detection_count_avg": 5.75, "frames_in_current_mode": 16, "frame_count": 16}, "1": {"fps_avg": 16.81, "infer_fps": 16.81, "latency_p95_ms": 68.87, "infer_latency_p95_ms": 68.87, "current_mode": "FULL", "detection_count_avg": 5.88, "frames_in_current_mode": 16, "frame_count": 16}, "2": {"fps_avg": 16.81, "infer_fps": 16.81, "latency_p95_ms": 69.0, "infer_latency_p95_ms": 69.0, "current_mode": "FULL", "detection_count_avg": 5.62, "frames_in_current_mode": 16, "frame_count": 16}, "3": {"fps_avg": 16.82, "infer_fps": 16.82, "latency_p95_ms": 68.96, "infer_latency_p95_ms": 68.96, "current_mode": "FULL", "detection_count_avg": 7.75, "frames_in_current_mode": 16, "frame_count": 16}}, "global": {"gpu_util_avg": 13.7, "n_active_streams": 4, "mem_used_mb": 5941.0, "n_streams_by_mode": {"FULL": 4, "LITE": 0, "SKIP": 0, "OFFLOAD": 0}}, "t_collect": 1773604588.424072}, "action": null, "n_active": 4, "mode_counts": {"FULL": 4, "LITE": 0, "SKIP": 0, "OFFLOAD": 0}}, {"step": 15, "t_elapsed": 16.09, "events": [], "observation": {"per_stream": {"0": {"fps_avg": 16.37, "infer_fps": 16.37, "latency_p95_ms": 71.07, "infer_latency_p95_ms": 71.07, "current_mode": "FULL", "detection_count_avg": 3.8, "frames_in_current_mode": 15, "frame_count": 15}, "1": {"fps_avg": 16.44, "infer_fps": 16.44, "latency_p95_ms": 72.15, "infer_latency_p95_ms": 72.15, "current_mode": "FULL", "detection_count_avg": 3.67, "frames_in_current_mode": 15, "frame_count": 15}, "2": {"fps_avg": 16.35, "infer_fps": 16.35, "latency_p95_ms": 71.65, "infer_latency_p95_ms": 71.65, "current_mode": "FULL", "detection_count_avg": 4.0, "frames_in_current_mode": 15, "frame_count": 15}, "3": {"fps_avg": 16.35, "infer_fps": 16.35, "latency_p95_ms": 71.51, "infer_latency_p95_ms": 71.51, "current_mode": "FULL", "detection_count_avg": 7.4, "frames_in_current_mode": 15, "frame_count": 15}}, "global": {"gpu_util_avg": 68.3, "n_active_streams": 4, "mem_used_mb": 5942.0, "n_streams_by_mode": {"FULL": 4, "LITE": 0, "SKIP": 0, "OFFLOAD": 0}}, "t_collect": 1773604589.4307125}, "action": null, "n_active": 4, "mode_counts": {"FULL": 4, "LITE": 0, "SKIP": 0, "OFFLOAD": 0}}, {"step": 16, "t_elapsed": 17.09, "events": [], "observation": {"per_stream": {"0": {"fps_avg": 16.17, "infer_fps": 16.17, "latency_p95_ms": 72.33, "infer_latency_p95_ms": 72.33, "current_mode": "FULL", "detection_count_avg": 4.38, "frames_in_current_mode": 16, "frame_count": 16}, "1": {"fps_avg": 16.2, "infer_fps": 16.2, "latency_p95_ms": 72.49, "infer_latency_p95_ms": 72.49, "current_mode": "FULL", "detection_count_avg": 4.44, "frames_in_current_mode": 16, "frame_count": 16}, "2": {"fps_avg": 16.2, "infer_fps": 16.2, "latency_p95_ms": 72.5, "infer_latency_p95_ms": 72.5, "current_mode": "FULL", "detection_count_avg": 4.31, "frames_in_current_mode": 16, "frame_count": 16}, "3": {"fps_avg": 16.17, "infer_fps": 16.17, "latency_p95_ms": 73.42, "infer_latency_p95_ms": 73.42, "current_mode": "FULL", "detection_count_avg": 8.25, "frames_in_current_mode": 16, "frame_count": 16}}, "global": {"gpu_util_avg": 86.2, "n_active_streams": 4, "mem_used_mb": 5944.0, "n_streams_by_mode": {"FULL": 4, "LITE": 0, "SKIP": 0, "OFFLOAD": 0}}, "t_collect": 1773604590.4347281}, "action": null, "n_active": 4, "mode_counts": {"FULL": 4, "LITE": 0, "SKIP": 0, "OFFLOAD": 0}}, {"step": 17, "t_elapsed": 18.1, "events": [], "observation": {"per_stream": {"0": {"fps_avg": 16.04, "infer_fps": 16.04, "latency_p95_ms": 71.35, "infer_latency_p95_ms": 71.35, "current_mode": "FULL", "detection_count_avg": 5.53, "frames_in_current_mode": 15, "frame_count": 15}, "1": {"fps_avg": 16.04, "infer_fps": 16.04, "latency_p95_ms": 71.69, "infer_latency_p95_ms": 71.69, "current_mode": "FULL", "detection_count_avg": 5.6, "frames_in_current_mode": 15, "frame_count": 15}, "2": {"fps_avg": 16.03, "infer_fps": 16.03, "latency_p95_ms": 71.36, "infer_latency_p95_ms": 71.36, "current_mode": "FULL", "detection_count_avg": 5.27, "frames_in_current_mode": 15, "frame_count": 15}, "3": {"fps_avg": 16.03, "infer_fps": 16.03, "latency_p95_ms": 71.43, "infer_latency_p95_ms": 71.43, "current_mode": "FULL", "detection_count_avg": 8.73, "frames_in_current_mode": 15, "frame_count": 15}}, "global": {"gpu_util_avg": 63.8, "n_active_streams": 4, "mem_used_mb": 5945.0, "n_streams_by_mode": {"FULL": 4, "LITE": 0, "SKIP": 0, "OFFLOAD": 0}}, "t_collect": 1773604591.4430172}, "action": null, "n_active": 4, "mode_counts": {"FULL": 4, "LITE": 0, "SKIP": 0, "OFFLOAD": 0}}, {"step": 18, "t_elapsed": 19.11, "events": [], "observation": {"per_stream": {"0": {"fps_avg": 16.42, "infer_fps": 16.42, "latency_p95_ms": 70.42, "infer_latency_p95_ms": 70.42, "current_mode": "FULL", "detection_count_avg": 6.87, "frames_in_current_mode": 15, "frame_count": 15}, "1": {"fps_avg": 16.42, "infer_fps": 16.42, "latency_p95_ms": 70.4, "infer_latency_p95_ms": 70.4, "current_mode": "FULL", "detection_count_avg": 6.87, "frames_in_current_mode": 15, "frame_count": 15}, "2": {"fps_avg": 16.39, "infer_fps": 16.39, "latency_p95_ms": 71.63, "infer_latency_p95_ms": 71.63, "current_mode": "FULL", "detection_count_avg": 7.0, "frames_in_current_mode": 15, "frame_count": 15}, "3": {"fps_avg": 16.43, "infer_fps": 16.43, "latency_p95_ms": 70.5, "infer_latency_p95_ms": 70.5, "current_mode": "FULL", "detection_count_avg": 9.33, "frames_in_current_mode": 15, "frame_count": 15}}, "global": {"gpu_util_avg": 56.0, "n_active_streams": 4, "mem_used_mb": 5947.0, "n_streams_by_mode": {"FULL": 4, "LITE": 0, "SKIP": 0, "OFFLOAD": 0}}, "t_collect": 1773604592.4502585}, "action": null, "n_active": 4, "mode_counts": {"FULL": 4, "LITE": 0, "SKIP": 0, "OFFLOAD": 0}}, {"step": 19, "t_elapsed": 20.11, "events": [], "observation": {"per_stream": {"0": {"fps_avg": 16.09, "infer_fps": 16.09, "latency_p95_ms": 73.1, "infer_latency_p95_ms": 73.1, "current_mode": "FULL", "detection_count_avg": 7.0, "frames_in_current_mode": 15, "frame_count": 15}, "1": {"fps_avg": 16.09, "infer_fps": 16.09, "latency_p95_ms": 73.68, "infer_latency_p95_ms": 73.68, "current_mode": "FULL", "detection_count_avg": 7.13, "frames_in_current_mode": 15, "frame_count": 15}, "2": {"fps_avg": 16.09, "infer_fps": 16.09, "latency_p95_ms": 73.66, "infer_latency_p95_ms": 73.66, "current_mode": "FULL", "detection_count_avg": 6.87, "frames_in_current_mode": 15, "frame_count": 15}, "3": {"fps_avg": 16.13, "infer_fps": 16.13, "latency_p95_ms": 74.03, "infer_latency_p95_ms": 74.03, "current_mode": "FULL", "detection_count_avg": 9.6, "frames_in_current_mode": 15, "frame_count": 15}}, "global": {"gpu_util_avg": 46.2, "n_active_streams": 4, "mem_used_mb": 5949.0, "n_streams_by_mode": {"FULL": 4, "LITE": 0, "SKIP": 0, "OFFLOAD": 0}}, "t_collect": 1773604593.4545481}, "action": null, "n_active": 4, "mode_counts": {"FULL": 4, "LITE": 0, "SKIP": 0, "OFFLOAD": 0}}, {"step": 20, "t_elapsed": 21.12, "events": ["add_stream"], "observation": {"per_stream": {"0": {"fps_avg": 11.63, "infer_fps": 11.63, "latency_p95_ms": 152.28, "infer_latency_p95_ms": 152.28, "current_mode": "FULL", "detection_count_avg": 7.09, "frames_in_current_mode": 11, "frame_count": 11}, "1": {"fps_avg": 10.57, "infer_fps": 10.57, "latency_p95_ms": 184.11, "infer_latency_p95_ms": 184.11, "current_mode": "FULL", "detection_count_avg": 7.0, "frames_in_current_mode": 10, "frame_count": 10}, "2": {"fps_avg": 10.56, "infer_fps": 10.56, "latency_p95_ms": 184.65, "infer_latency_p95_ms": 184.65, "current_mode": "FULL", "detection_count_avg": 7.2, "frames_in_current_mode": 10, "frame_count": 10}, "3": {"fps_avg": 10.57, "infer_fps": 10.57, "latency_p95_ms": 179.2, "infer_latency_p95_ms": 179.2, "current_mode": "FULL", "detection_count_avg": 9.0, "frames_in_current_mode": 10, "frame_count": 10}, "4": {"fps_avg": 13.4, "infer_fps": 13.4, "latency_p95_ms": 201.87, "infer_latency_p95_ms": 201.87, "current_mode": "FULL", "detection_count_avg": 5.89, "frames_in_current_mode": 9, "frame_count": 9}}, "global": {"gpu_util_avg": 43.4, "n_active_streams": 5, "mem_used_mb": 5964.0, "n_streams_by_mode": {"FULL": 5, "LITE": 0, "SKIP": 0, "OFFLOAD": 0}}, "t_collect": 1773604594.4598074}, "action": {"stream_id": 2, "from_mode": "FULL", "to_mode": "LITE", "dwell_was": 20}, "n_active": 5, "mode_counts": {"FULL": 5, "LITE": 0, "SKIP": 0, "OFFLOAD": 0}}, {"step": 21, "t_elapsed": 22.13, "events": [], "observation": {"per_stream": {"0": {"fps_avg": 13.57, "infer_fps": 13.57, "latency_p95_ms": 87.87, "infer_latency_p95_ms": 87.87, "current_mode": "FULL", "detection_count_avg": 7.58, "frames_in_current_mode": 12, "frame_count": 12}, "1": {"fps_avg": 13.57, "infer_fps": 13.57, "latency_p95_ms": 86.36, "infer_latency_p95_ms": 86.36, "current_mode": "FULL", "detection_count_avg": 7.58, "frames_in_current_mode": 12, "frame_count": 12}, "2": {"fps_avg": 11.62, "infer_fps": 11.62, "latency_p95_ms": 190.5, "infer_latency_p95_ms": 190.5, "current_mode": "LITE", "detection_count_avg": 3.91, "frames_in_current_mode": 11, "frame_count": 11}, "3": {"fps_avg": 13.53, "infer_fps": 13.53, "latency_p95_ms": 86.28, "infer_latency_p95_ms": 86.28, "current_mode": "FULL", "detection_count_avg": 8.75, "frames_in_current_mode": 12, "frame_count": 12}, "4": {"fps_avg": 13.59, "infer_fps": 13.59, "latency_p95_ms": 86.18, "infer_latency_p95_ms": 86.18, "current_mode": "FULL", "detection_count_avg": 6.08, "frames_in_current_mode": 12, "frame_count": 12}}, "global": {"gpu_util_avg": 79.6, "n_active_streams": 5, "mem_used_mb": 5965.0, "n_streams_by_mode": {"FULL": 4, "LITE": 1, "SKIP": 0, "OFFLOAD": 0}}, "t_collect": 1773604595.465781}, "action": {"stream_id": 4, "from_mode": "FULL", "to_mode": "LITE", "dwell_was": 1}, "n_active": 5, "mode_counts": {"FULL": 4, "LITE": 1, "SKIP": 0, "OFFLOAD": 0}}, {"step": 22, "t_elapsed": 23.13, "events": [], "observation": {"per_stream": {"0": {"fps_avg": 16.4, "infer_fps": 16.4, "latency_p95_ms": 81.25, "infer_latency_p95_ms": 81.25, "current_mode": "FULL", "detection_count_avg": 7.33, "frames_in_current_mode": 15, "frame_count": 15}, "1": {"fps_avg": 16.4, "infer_fps": 16.4, "latency_p95_ms": 81.08, "infer_latency_p95_ms": 81.08, "current_mode": "FULL", "detection_count_avg": 7.33, "frames_in_current_mode": 15, "frame_count": 15}, "2": {"fps_avg": 13.15, "infer_fps": 13.15, "latency_p95_ms": 164.96, "infer_latency_p95_ms": 164.96, "current_mode": "LITE", "detection_count_avg": 4.0, "frames_in_current_mode": 12, "frame_count": 12}, "3": {"fps_avg": 16.44, "infer_fps": 16.44, "latency_p95_ms": 79.24, "infer_latency_p95_ms": 79.24, "current_mode": "FULL", "detection_count_avg": 6.67, "frames_in_current_mode": 15, "frame_count": 15}, "4": {"fps_avg": 12.35, "infer_fps": 12.35, "latency_p95_ms": 193.17, "infer_latency_p95_ms": 193.17, "current_mode": "LITE", "detection_count_avg": 4.83, "frames_in_current_mode": 12, "frame_count": 12}}, "global": {"gpu_util_avg": 56.8, "n_active_streams": 5, "mem_used_mb": 5962.0, "n_streams_by_mode": {"FULL": 3, "LITE": 2, "SKIP": 0, "OFFLOAD": 0}}, "t_collect": 1773604596.4765403}, "action": {"stream_id": 0, "from_mode": "FULL", "to_mode": "LITE", "dwell_was": 22}, "n_active": 5, "mode_counts": {"FULL": 3, "LITE": 2, "SKIP": 0, "OFFLOAD": 0}}, {"step": 23, "t_elapsed": 24.14, "events": [], "observation": {"per_stream": {"0": {"fps_avg": 13.67, "infer_fps": 13.67, "latency_p95_ms": 159.31, "infer_latency_p95_ms": 159.31, "current_mode": "LITE", "detection_count_avg": 6.0, "frames_in_current_mode": 13, "frame_count": 13}, "1": {"fps_avg": 19.19, "infer_fps": 19.19, "latency_p95_ms": 63.75, "infer_latency_p95_ms": 63.75, "current_mode": "FULL", "detection_count_avg": 8.58, "frames_in_current_mode": 19, "frame_count": 19}, "2": {"fps_avg": 14.29, "infer_fps": 14.29, "latency_p95_ms": 136.08, "infer_latency_p95_ms": 136.08, "current_mode": "LITE", "detection_count_avg": 5.54, "frames_in_current_mode": 13, "frame_count": 13}, "3": {"fps_avg": 19.19, "infer_fps": 19.19, "latency_p95_ms": 64.83, "infer_latency_p95_ms": 64.83, "current_mode": "FULL", "detection_count_avg": 6.05, "frames_in_current_mode": 19, "frame_count": 19}, "4": {"fps_avg": 14.29, "infer_fps": 14.29, "latency_p95_ms": 136.02, "infer_latency_p95_ms": 136.02, "current_mode": "LITE", "detection_count_avg": 5.69, "frames_in_current_mode": 13, "frame_count": 13}}, "global": {"gpu_util_avg": 54.8, "n_active_streams": 5, "mem_used_mb": 5962.0, "n_streams_by_mode": {"FULL": 2, "LITE": 3, "SKIP": 0, "OFFLOAD": 0}}, "t_collect": 1773604597.4826782}, "action": {"stream_id": 1, "from_mode": "FULL", "to_mode": "LITE", "dwell_was": 23}, "n_active": 5, "mode_counts": {"FULL": 2, "LITE": 3, "SKIP": 0, "OFFLOAD": 0}}, {"step": 24, "t_elapsed": 25.15, "events": [], "observation": {"per_stream": {"0": {"fps_avg": 13.3, "infer_fps": 13.3, "latency_p95_ms": 135.5, "infer_latency_p95_ms": 135.5, "current_mode": "LITE", "detection_count_avg": 4.69, "frames_in_current_mode": 13, "frame_count": 13}, "1": {"fps_avg": 12.7, "infer_fps": 12.7, "latency_p95_ms": 158.8, "infer_latency_p95_ms": 158.8, "current_mode": "LITE", "detection_count_avg": 5.0, "frames_in_current_mode": 12, "frame_count": 12}, "2": {"fps_avg": 13.3, "infer_fps": 13.3, "latency_p95_ms": 135.94, "infer_latency_p95_ms": 135.94, "current_mode": "LITE", "detection_count_avg": 5.15, "frames_in_current_mode": 13, "frame_count": 13}, "3": {"fps_avg": 22.76, "infer_fps": 22.76, "latency_p95_ms": 57.98, "infer_latency_p95_ms": 57.98, "current_mode": "FULL", "detection_count_avg": 4.71, "frames_in_current_mode": 21, "frame_count": 21}, "4": {"fps_avg": 13.28, "infer_fps": 13.28, "latency_p95_ms": 140.2, "infer_latency_p95_ms": 140.2, "current_mode": "LITE", "detection_count_avg": 5.38, "frames_in_current_mode": 13, "frame_count": 13}}, "global": {"gpu_util_avg": 54.5, "n_active_streams": 5, "mem_used_mb": 5965.0, "n_streams_by_mode": {"FULL": 1, "LITE": 4, "SKIP": 0, "OFFLOAD": 0}}, "t_collect": 1773604598.4901884}, "action": {"stream_id": 3, "from_mode": "FULL", "to_mode": "LITE", "dwell_was": 14}, "n_active": 5, "mode_counts": {"FULL": 1, "LITE": 4, "SKIP": 0, "OFFLOAD": 0}}, {"step": 25, "t_elapsed": 26.15, "events": [], "observation": {"per_stream": {"0": {"fps_avg": 12.79, "infer_fps": 12.79, "latency_p95_ms": 146.39, "infer_latency_p95_ms": 146.39, "current_mode": "LITE", "detection_count_avg": 6.75, "frames_in_current_mode": 12, "frame_count": 12}, "1": {"fps_avg": 14.84, "infer_fps": 14.84, "latency_p95_ms": 117.82, "infer_latency_p95_ms": 117.82, "current_mode": "LITE", "detection_count_avg": 6.71, "frames_in_current_mode": 14, "frame_count": 14}, "2": {"fps_avg": 13.86, "infer_fps": 13.86, "latency_p95_ms": 143.64, "infer_latency_p95_ms": 143.64, "current_mode": "LITE", "detection_count_avg": 5.38, "frames_in_current_mode": 13, "frame_count": 13}, "3": {"fps_avg": 13.42, "infer_fps": 13.42, "latency_p95_ms": 141.86, "infer_latency_p95_ms": 141.86, "current_mode": "LITE", "detection_count_avg": 2.0, "frames_in_current_mode": 13, "frame_count": 13}, "4": {"fps_avg": 12.8, "infer_fps": 12.8, "latency_p95_ms": 168.07, "infer_latency_p95_ms": 168.07, "current_mode": "LITE", "detection_count_avg": 4.5, "frames_in_current_mode": 12, "frame_count": 12}}, "global": {"gpu_util_avg": 44.0, "n_active_streams": 5, "mem_used_mb": 5967.0, "n_streams_by_mode": {"FULL": 0, "LITE": 5, "SKIP": 0, "OFFLOAD": 0}}, "t_collect": 1773604599.499115}, "action": null, "n_active": 5, "mode_counts": {"FULL": 0, "LITE": 5, "SKIP": 0, "OFFLOAD": 0}}, {"step": 26, "t_elapsed": 27.16, "events": [], "observation": {"per_stream": {"0": {"fps_avg": 16.73, "infer_fps": 16.73, "latency_p95_ms": 70.64, "infer_latency_p95_ms": 70.64, "current_mode": "LITE", "detection_count_avg": 6.67, "frames_in_current_mode": 15, "frame_count": 15}, "1": {"fps_avg": 16.73, "infer_fps": 16.73, "latency_p95_ms": 67.43, "infer_latency_p95_ms": 67.43, "current_mode": "LITE", "detection_count_avg": 7.33, "frames_in_current_mode": 15, "frame_count": 15}, "2": {"fps_avg": 16.73, "infer_fps": 16.73, "latency_p95_ms": 69.66, "infer_latency_p95_ms": 69.66, "current_mode": "LITE", "detection_count_avg": 6.67, "frames_in_current_mode": 15, "frame_count": 15}, "3": {"fps_avg": 16.73, "infer_fps": 16.73, "latency_p95_ms": 70.21, "infer_latency_p95_ms": 70.21, "current_mode": "LITE", "detection_count_avg": 1.09, "frames_in_current_mode": 15, "frame_count": 15}, "4": {"fps_avg": 16.68, "infer_fps": 16.68, "latency_p95_ms": 70.17, "infer_latency_p95_ms": 70.17, "current_mode": "LITE", "detection_count_avg": 3.47, "frames_in_current_mode": 15, "frame_count": 15}}, "global": {"gpu_util_avg": 44.4, "n_active_streams": 5, "mem_used_mb": 5968.0, "n_streams_by_mode": {"FULL": 0, "LITE": 5, "SKIP": 0, "OFFLOAD": 0}}, "t_collect": 1773604600.5035222}, "action": null, "n_active": 5, "mode_counts": {"FULL": 0, "LITE": 5, "SKIP": 0, "OFFLOAD": 0}}, {"step": 27, "t_elapsed": 28.17, "events": [], "observation": {"per_stream": {"0": {"fps_avg": 16.94, "infer_fps": 16.94, "latency_p95_ms": 70.77, "infer_latency_p95_ms": 70.77, "current_mode": "LITE", "detection_count_avg": 6.69, "frames_in_current_mode": 16, "frame_count": 16}, "1": {"fps_avg": 14.82, "infer_fps": 14.82, "latency_p95_ms": 109.9, "infer_latency_p95_ms": 109.9, "current_mode": "LITE", "detection_count_avg": 5.93, "frames_in_current_mode": 14, "frame_count": 14}, "2": {"fps_avg": 15.85, "infer_fps": 15.85, "latency_p95_ms": 84.11, "infer_latency_p95_ms": 84.11, "current_mode": "LITE", "detection_count_avg": 7.13, "frames_in_current_mode": 15, "frame_count": 15}, "3": {"fps_avg": 15.88, "infer_fps": 15.88, "latency_p95_ms": 83.29, "infer_latency_p95_ms": 83.29, "current_mode": "LITE", "detection_count_avg": 2.13, "frames_in_current_mode": 15, "frame_count": 15}, "4": {"fps_avg": 15.66, "infer_fps": 15.66, "latency_p95_ms": 110.96, "infer_latency_p95_ms": 110.96, "current_mode": "LITE", "detection_count_avg": 5.07, "frames_in_current_mode": 14, "frame_count": 14}}, "global": {"gpu_util_avg": 22.9, "n_active_streams": 5, "mem_used_mb": 5968.0, "n_streams_by_mode": {"FULL": 0, "LITE": 5, "SKIP": 0, "OFFLOAD": 0}}, "t_collect": 1773604601.5082128}, "action": null, "n_active": 5, "mode_counts": {"FULL": 0, "LITE": 5, "SKIP": 0, "OFFLOAD": 0}}, {"step": 28, "t_elapsed": 29.17, "events": [], "observation": {"per_stream": {"0": {"fps_avg": 15.8, "infer_fps": 15.8, "latency_p95_ms": 82.95, "infer_latency_p95_ms": 82.95, "current_mode": "LITE", "detection_count_avg": 4.87, "frames_in_current_mode": 15, "frame_count": 15}, "1": {"fps_avg": 14.76, "infer_fps": 14.76, "latency_p95_ms": 110.79, "infer_latency_p95_ms": 110.79, "current_mode": "LITE", "detection_count_avg": 4.43, "frames_in_current_mode": 14, "frame_count": 14}, "2": {"fps_avg": 15.92, "infer_fps": 15.92, "latency_p95_ms": 79.01, "infer_latency_p95_ms": 79.01, "current_mode": "LITE", "detection_count_avg": 5.53, "frames_in_current_mode": 15, "frame_count": 15}, "3": {"fps_avg": 16.88, "infer_fps": 16.88, "latency_p95_ms": 70.25, "infer_latency_p95_ms": 70.25, "current_mode": "LITE", "detection_count_avg": 2.12, "frames_in_current_mode": 16, "frame_count": 16}, "4": {"fps_avg": 15.82, "infer_fps": 15.82, "latency_p95_ms": 82.97, "infer_latency_p95_ms": 82.97, "current_mode": "LITE", "detection_count_avg": 5.47, "frames_in_current_mode": 15, "frame_count": 15}}, "global": {"gpu_util_avg": 32.8, "n_active_streams": 5, "mem_used_mb": 5968.0, "n_streams_by_mode": {"FULL": 0, "LITE": 5, "SKIP": 0, "OFFLOAD": 0}}, "t_collect": 1773604602.516378}, "action": null, "n_active": 5, "mode_counts": {"FULL": 0, "LITE": 5, "SKIP": 0, "OFFLOAD": 0}}, {"step": 29, "t_elapsed": 30.18, "events": [], "observation": {"per_stream": {"0": {"fps_avg": 16.09, "infer_fps": 16.09, "latency_p95_ms": 70.76, "infer_latency_p95_ms": 70.76, "current_mode": "LITE", "detection_count_avg": 3.07, "frames_in_current_mode": 15, "frame_count": 15}, "1": {"fps_avg": 16.03, "infer_fps": 16.03, "latency_p95_ms": 70.82, "infer_latency_p95_ms": 70.82, "current_mode": "LITE", "detection_count_avg": 2.87, "frames_in_current_mode": 15, "frame_count": 15}, "2": {"fps_avg": 16.03, "infer_fps": 16.03, "latency_p95_ms": 70.3, "infer_latency_p95_ms": 70.3, "current_mode": "LITE", "detection_count_avg": 3.87, "frames_in_current_mode": 15, "frame_count": 15}, "3": {"fps_avg": 16.03, "infer_fps": 16.03, "latency_p95_ms": 70.91, "infer_latency_p95_ms": 70.91, "current_mode": "LITE", "detection_count_avg": 2.33, "frames_in_current_mode": 15, "frame_count": 15}, "4": {"fps_avg": 15.98, "infer_fps": 15.98, "latency_p95_ms": 73.74, "infer_latency_p95_ms": 73.74, "current_mode": "LITE", "detection_count_avg": 6.8, "frames_in_current_mode": 15, "frame_count": 15}}, "global": {"gpu_util_avg": 52.6, "n_active_streams": 5, "mem_used_mb": 5968.0, "n_streams_by_mode": {"FULL": 0, "LITE": 5, "SKIP": 0, "OFFLOAD": 0}}, "t_collect": 1773604603.5212696}, "action": null, "n_active": 5, "mode_counts": {"FULL": 0, "LITE": 5, "SKIP": 0, "OFFLOAD": 0}}, {"step": 30, "t_elapsed": 31.19, "events": ["add_stream"], "observation": {"per_stream": {"0": {"fps_avg": 13.09, "infer_fps": 13.09, "latency_p95_ms": 93.71, "infer_latency_p95_ms": 93.71, "current_mode": "LITE", "detection_count_avg": 3.25, "frames_in_current_mode": 12, "frame_count": 12}, "1": {"fps_avg": 13.09, "infer_fps": 13.09, "latency_p95_ms": 96.63, "infer_latency_p95_ms": 96.63, "current_mode": "LITE", "detection_count_avg": 3.25, "frames_in_current_mode": 12, "frame_count": 12}, "2": {"fps_avg": 13.06, "infer_fps": 13.06, "latency_p95_ms": 94.6, "infer_latency_p95_ms": 94.6, "current_mode": "LITE", "detection_count_avg": 2.75, "frames_in_current_mode": 12, "frame_count": 12}, "3": {"fps_avg": 13.09, "infer_fps": 13.09, "latency_p95_ms": 94.63, "infer_latency_p95_ms": 94.63, "current_mode": "LITE", "detection_count_avg": 3.17, "frames_in_current_mode": 12, "frame_count": 12}, "4": {"fps_avg": 13.18, "infer_fps": 13.18, "latency_p95_ms": 93.76, "infer_latency_p95_ms": 93.76, "current_mode": "LITE", "detection_count_avg": 6.08, "frames_in_current_mode": 12, "frame_count": 12}, "5": {"fps_avg": 16.56, "infer_fps": 16.56, "latency_p95_ms": 98.66, "infer_latency_p95_ms": 98.66, "current_mode": "FULL", "detection_count_avg": 6.07, "frames_in_current_mode": 14, "frame_count": 14}}, "global": {"gpu_util_avg": 30.4, "n_active_streams": 6, "mem_used_mb": 5980.0, "n_streams_by_mode": {"FULL": 1, "LITE": 5, "SKIP": 0, "OFFLOAD": 0}}, "t_collect": 1773604604.5294502}, "action": {"stream_id": 0, "from_mode": "LITE", "to_mode": "OFFLOAD", "dwell_was": 8}, "n_active": 6, "mode_counts": {"FULL": 1, "LITE": 5, "SKIP": 0, "OFFLOAD": 0}}, {"step": 31, "t_elapsed": 32.2, "events": [], "observation": {"per_stream": {"0": {"fps_avg": 10.11, "infer_fps": 10.11, "latency_p95_ms": 141.93, "infer_latency_p95_ms": 141.93, "current_mode": "OFFLOAD", "detection_count_avg": 5.22, "frames_in_current_mode": 9, "frame_count": 9}, "1": {"fps_avg": 14.41, "infer_fps": 14.41, "latency_p95_ms": 99.04, "infer_latency_p95_ms": 99.04, "current_mode": "LITE", "detection_count_avg": 1.93, "frames_in_current_mode": 14, "frame_count": 14}, "2": {"fps_avg": 14.4, "infer_fps": 14.4, "latency_p95_ms": 99.08, "infer_latency_p95_ms": 99.08, "current_mode": "LITE", "detection_count_avg": 3.14, "frames_in_current_mode": 14, "frame_count": 14}, "3": {"fps_avg": 15.48, "infer_fps": 15.48, "latency_p95_ms": 102.17, "infer_latency_p95_ms": 102.17, "current_mode": "LITE", "detection_count_avg": 3.07, "frames_in_current_mode": 14, "frame_count": 14}, "4": {"fps_avg": 14.41, "infer_fps": 14.41, "latency_p95_ms": 101.91, "infer_latency_p95_ms": 101.91, "current_mode": "LITE", "detection_count_avg": 5.93, "frames_in_current_mode": 14, "frame_count": 14}, "5": {"fps_avg": 21.14, "infer_fps": 21.14, "latency_p95_ms": 65.13, "infer_latency_p95_ms": 65.13, "current_mode": "FULL", "detection_count_avg": 7.05, "frames_in_current_mode": 20, "frame_count": 20}}, "global": {"gpu_util_avg": 43.0, "n_active_streams": 6, "mem_used_mb": 5985.0, "n_streams_by_mode": {"FULL": 1, "LITE": 4, "SKIP": 0, "OFFLOAD": 1}}, "t_collect": 1773604605.536457}, "action": {"stream_id": 5, "from_mode": "FULL", "to_mode": "LITE", "dwell_was": 1}, "n_active": 6, "mode_counts": {"FULL": 1, "LITE": 4, "SKIP": 0, "OFFLOAD": 1}}, {"step": 32, "t_elapsed": 33.21, "events": [], "observation": {"per_stream": {"0": {"fps_avg": 11.45, "infer_fps": 11.45, "latency_p95_ms": 109.62, "infer_latency_p95_ms": 109.62, "current_mode": "OFFLOAD", "detection_count_avg": 4.7, "frames_in_current_mode": 10, "frame_count": 10}, "1": {"fps_avg": 15.49, "infer_fps": 15.49, "latency_p95_ms": 110.1, "infer_latency_p95_ms": 110.1, "current_mode": "LITE", "detection_count_avg": 2.07, "frames_in_current_mode": 14, "frame_count": 14}, "2": {"fps_avg": 17.68, "infer_fps": 17.68, "latency_p95_ms": 82.6, "infer_latency_p95_ms": 82.6, "current_mode": "LITE", "detection_count_avg": 1.81, "frames_in_current_mode": 16, "frame_count": 16}, "3": {"fps_avg": 18.73, "infer_fps": 18.73, "latency_p95_ms": 66.43, "infer_latency_p95_ms": 66.43, "current_mode": "LITE", "detection_count_avg": 4.0, "frames_in_current_mode": 17, "frame_count": 17}, "4": {"fps_avg": 16.53, "infer_fps": 16.53, "latency_p95_ms": 103.73, "infer_latency_p95_ms": 103.73, "current_mode": "LITE", "detection_count_avg": 5.13, "frames_in_current_mode": 15, "frame_count": 15}, "5": {"fps_avg": 17.53, "infer_fps": 17.53, "latency_p95_ms": 72.25, "infer_latency_p95_ms": 72.25, "current_mode": "LITE", "detection_count_avg": 5.69, "frames_in_current_mode": 16, "frame_count": 16}}, "global": {"gpu_util_avg": 46.1, "n_active_streams": 6, "mem_used_mb": 5984.0, "n_streams_by_mode": {"FULL": 0, "LITE": 5, "SKIP": 0, "OFFLOAD": 1}}, "t_collect": 1773604606.5481954}, "action": {"stream_id": 0, "from_mode": "OFFLOAD", "to_mode": "LITE", "dwell_was": 2}, "n_active": 6, "mode_counts": {"FULL": 0, "LITE": 5, "SKIP": 0, "OFFLOAD": 1}}, {"step": 33, "t_elapsed": 34.21, "events": [], "observation": {"per_stream": {"0": {"fps_avg": 11.64, "infer_fps": 11.64, "latency_p95_ms": 160.55, "infer_latency_p95_ms": 160.55, "current_mode": "LITE", "detection_count_avg": 2.36, "frames_in_current_mode": 11, "frame_count": 11}, "1": {"fps_avg": 11.54, "infer_fps": 11.54, "latency_p95_ms": 190.07, "infer_latency_p95_ms": 190.07, "current_mode": "LITE", "detection_count_avg": 2.18, "frames_in_current_mode": 11, "frame_count": 11}, "2": {"fps_avg": 12.58, "infer_fps": 12.58, "latency_p95_ms": 157.26, "infer_latency_p95_ms": 157.26, "current_mode": "LITE", "detection_count_avg": 2.08, "frames_in_current_mode": 12, "frame_count": 12}, "3": {"fps_avg": 12.53, "infer_fps": 12.53, "latency_p95_ms": 160.13, "infer_latency_p95_ms": 160.13, "current_mode": "LITE", "detection_count_avg": 5.67, "frames_in_current_mode": 12, "frame_count": 12}, "4": {"fps_avg": 13.63, "infer_fps": 13.63, "latency_p95_ms": 132.56, "infer_latency_p95_ms": 132.56, "current_mode": "LITE", "detection_count_avg": 4.54, "frames_in_current_mode": 13, "frame_count": 13}, "5": {"fps_avg": 11.58, "infer_fps": 11.58, "latency_p95_ms": 186.82, "infer_latency_p95_ms": 186.82, "current_mode": "LITE", "detection_count_avg": 5.09, "frames_in_current_mode": 11, "frame_count": 11}}, "global": {"gpu_util_avg": 18.2, "n_active_streams": 6, "mem_used_mb": 5984.0, "n_streams_by_mode": {"FULL": 0, "LITE": 6, "SKIP": 0, "OFFLOAD": 0}}, "t_collect": 1773604607.5534925}, "action": null, "n_active": 6, "mode_counts": {"FULL": 0, "LITE": 6, "SKIP": 0, "OFFLOAD": 0}}, {"step": 34, "t_elapsed": 35.22, "events": [], "observation": {"per_stream": {"0": {"fps_avg": 14.54, "infer_fps": 14.54, "latency_p95_ms": 82.74, "infer_latency_p95_ms": 82.74, "current_mode": "LITE", "detection_count_avg": 2.14, "frames_in_current_mode": 14, "frame_count": 14}, "1": {"fps_avg": 14.5, "infer_fps": 14.5, "latency_p95_ms": 81.92, "infer_latency_p95_ms": 81.92, "current_mode": "LITE", "detection_count_avg": 2.29, "frames_in_current_mode": 14, "frame_count": 14}, "2": {"fps_avg": 14.53, "infer_fps": 14.53, "latency_p95_ms": 85.0, "infer_latency_p95_ms": 85.0, "current_mode": "LITE", "detection_count_avg": 2.07, "frames_in_current_mode": 14, "frame_count": 14}, "3": {"fps_avg": 14.5, "infer_fps": 14.5, "latency_p95_ms": 80.86, "infer_latency_p95_ms": 80.86, "current_mode": "LITE", "detection_count_avg": 5.07, "frames_in_current_mode": 14, "frame_count": 14}, "4": {"fps_avg": 14.54, "infer_fps": 14.54, "latency_p95_ms": 80.19, "infer_latency_p95_ms": 80.19, "current_mode": "LITE", "detection_count_avg": 3.64, "frames_in_current_mode": 14, "frame_count": 14}, "5": {"fps_avg": 14.54, "infer_fps": 14.54, "latency_p95_ms": 80.21, "infer_latency_p95_ms": 80.21, "current_mode": "LITE", "detection_count_avg": 4.07, "frames_in_current_mode": 14, "frame_count": 14}}, "global": {"gpu_util_avg": 64.5, "n_active_streams": 6, "mem_used_mb": 5984.0, "n_streams_by_mode": {"FULL": 0, "LITE": 6, "SKIP": 0, "OFFLOAD": 0}}, "t_collect": 1773604608.566249}, "action": null, "n_active": 6, "mode_counts": {"FULL": 0, "LITE": 6, "SKIP": 0, "OFFLOAD": 0}}, {"step": 35, "t_elapsed": 36.23, "events": [], "observation": {"per_stream": {"0": {"fps_avg": 13.91, "infer_fps": 13.91, "latency_p95_ms": 99.82, "infer_latency_p95_ms": 99.82, "current_mode": "LITE", "detection_count_avg": 2.25, "frames_in_current_mode": 12, "frame_count": 12}, "1": {"fps_avg": 15.15, "infer_fps": 15.15, "latency_p95_ms": 83.66, "infer_latency_p95_ms": 83.66, "current_mode": "LITE", "detection_count_avg": 2.0, "frames_in_current_mode": 13, "frame_count": 13}, "2": {"fps_avg": 15.13, "infer_fps": 15.13, "latency_p95_ms": 86.42, "infer_latency_p95_ms": 86.42, "current_mode": "LITE", "detection_count_avg": 2.54, "frames_in_current_mode": 13, "frame_count": 13}, "3": {"fps_avg": 14.02, "infer_fps": 14.02, "latency_p95_ms": 98.74, "infer_latency_p95_ms": 98.74, "current_mode": "LITE", "detection_count_avg": 5.5, "frames_in_current_mode": 12, "frame_count": 12}, "4": {"fps_avg": 13.97, "infer_fps": 13.97, "latency_p95_ms": 100.0, "infer_latency_p95_ms": 100.0, "current_mode": "LITE", "detection_count_avg": 3.08, "frames_in_current_mode": 12, "frame_count": 12}, "5": {"fps_avg": 13.96, "infer_fps": 13.96, "latency_p95_ms": 98.1, "infer_latency_p95_ms": 98.1, "current_mode": "LITE", "detection_count_avg": 3.67, "frames_in_current_mode": 12, "frame_count": 12}}, "global": {"gpu_util_avg": 50.4, "n_active_streams": 6, "mem_used_mb": 5984.0, "n_streams_by_mode": {"FULL": 0, "LITE": 6, "SKIP": 0, "OFFLOAD": 0}}, "t_collect": 1773604609.5729651}, "action": null, "n_active": 6, "mode_counts": {"FULL": 0, "LITE": 6, "SKIP": 0, "OFFLOAD": 0}}, {"step": 36, "t_elapsed": 37.25, "events": [], "observation": {"per_stream": {"0": {"fps_avg": 14.14, "infer_fps": 14.14, "latency_p95_ms": 95.59, "infer_latency_p95_ms": 95.59, "current_mode": "LITE", "detection_count_avg": 2.07, "frames_in_current_mode": 14, "frame_count": 14}, "1": {"fps_avg": 14.28, "infer_fps": 14.28, "latency_p95_ms": 98.54, "infer_latency_p95_ms": 98.54, "current_mode": "LITE", "detection_count_avg": 2.92, "frames_in_current_mode": 13, "frame_count": 13}, "2": {"fps_avg": 14.2, "infer_fps": 14.2, "latency_p95_ms": 97.63, "infer_latency_p95_ms": 97.63, "current_mode": "LITE", "detection_count_avg": 2.21, "frames_in_current_mode": 14, "frame_count": 14}, "3": {"fps_avg": 14.14, "infer_fps": 14.14, "latency_p95_ms": 94.64, "infer_latency_p95_ms": 94.64, "current_mode": "LITE", "detection_count_avg": 6.71, "frames_in_current_mode": 14, "frame_count": 14}, "4": {"fps_avg": 15.15, "infer_fps": 15.15, "latency_p95_ms": 84.3, "infer_latency_p95_ms": 84.3, "current_mode": "LITE", "detection_count_avg": 3.93, "frames_in_current_mode": 15, "frame_count": 15}, "5": {"fps_avg": 14.14, "infer_fps": 14.14, "latency_p95_ms": 94.9, "infer_latency_p95_ms": 94.9, "current_mode": "LITE", "detection_count_avg": 5.07, "frames_in_current_mode": 14, "frame_count": 14}}, "global": {"gpu_util_avg": 19.7, "n_active_streams": 6, "mem_used_mb": 5989.0, "n_streams_by_mode": {"FULL": 0, "LITE": 6, "SKIP": 0, "OFFLOAD": 0}}, "t_collect": 1773604610.5804205}, "action": null, "n_active": 6, "mode_counts": {"FULL": 0, "LITE": 6, "SKIP": 0, "OFFLOAD": 0}}, {"step": 37, "t_elapsed": 38.26, "events": [], "observation": {"per_stream": {"0": {"fps_avg": 15.07, "infer_fps": 15.07, "latency_p95_ms": 79.97, "infer_latency_p95_ms": 79.97, "current_mode": "LITE", "detection_count_avg": 2.93, "frames_in_current_mode": 14, "frame_count": 14}, "1": {"fps_avg": 15.1, "infer_fps": 15.1, "latency_p95_ms": 85.42, "infer_latency_p95_ms": 85.42, "current_mode": "LITE", "detection_count_avg": 2.47, "frames_in_current_mode": 15, "frame_count": 15}, "2": {"fps_avg": 13.99, "infer_fps": 13.99, "latency_p95_ms": 99.7, "infer_latency_p95_ms": 99.7, "current_mode": "LITE", "detection_count_avg": 2.85, "frames_in_current_mode": 13, "frame_count": 13}, "3": {"fps_avg": 13.96, "infer_fps": 13.96, "latency_p95_ms": 100.16, "infer_latency_p95_ms": 100.16, "current_mode": "LITE", "detection_count_avg": 7.23, "frames_in_current_mode": 13, "frame_count": 13}, "4": {"fps_avg": 14.0, "infer_fps": 14.0, "latency_p95_ms": 97.86, "infer_latency_p95_ms": 97.86, "current_mode": "LITE", "detection_count_avg": 1.77, "frames_in_current_mode": 13, "frame_count": 13}, "5": {"fps_avg": 13.95, "infer_fps": 13.95, "latency_p95_ms": 101.12, "infer_latency_p95_ms": 101.12, "current_mode": "LITE", "detection_count_avg": 5.46, "frames_in_current_mode": 13, "frame_count": 13}}, "global": {"gpu_util_avg": 32.9, "n_active_streams": 6, "mem_used_mb": 5990.0, "n_streams_by_mode": {"FULL": 0, "LITE": 6, "SKIP": 0, "OFFLOAD": 0}}, "t_collect": 1773604611.5989165}, "action": null, "n_active": 6, "mode_counts": {"FULL": 0, "LITE": 6, "SKIP": 0, "OFFLOAD": 0}}, {"step": 38, "t_elapsed": 39.26, "events": [], "observation": {"per_stream": {"0": {"fps_avg": 13.38, "infer_fps": 13.38, "latency_p95_ms": 119.09, "infer_latency_p95_ms": 119.09, "current_mode": "LITE", "detection_count_avg": 2.5, "frames_in_current_mode": 12, "frame_count": 12}, "1": {"fps_avg": 14.54, "infer_fps": 14.54, "latency_p95_ms": 118.72, "infer_latency_p95_ms": 118.72, "current_mode": "LITE", "detection_count_avg": 1.5, "frames_in_current_mode": 13, "frame_count": 13}, "2": {"fps_avg": 12.33, "infer_fps": 12.33, "latency_p95_ms": 119.79, "infer_latency_p95_ms": 119.79, "current_mode": "LITE", "detection_count_avg": 2.18, "frames_in_current_mode": 11, "frame_count": 11}, "3": {"fps_avg": 15.39, "infer_fps": 15.39, "latency_p95_ms": 92.34, "infer_latency_p95_ms": 92.34, "current_mode": "LITE", "detection_count_avg": 6.08, "frames_in_current_mode": 13, "frame_count": 13}, "4": {"fps_avg": 14.2, "infer_fps": 14.2, "latency_p95_ms": 118.79, "infer_latency_p95_ms": 118.79, "current_mode": "LITE", "detection_count_avg": 1.11, "frames_in_current_mode": 12, "frame_count": 12}, "5": {"fps_avg": 15.44, "infer_fps": 15.44, "latency_p95_ms": 89.67, "infer_latency_p95_ms": 89.67, "current_mode": "LITE", "detection_count_avg": 6.46, "frames_in_current_mode": 13, "frame_count": 13}}, "global": {"gpu_util_avg": 38.1, "n_active_streams": 6, "mem_used_mb": 5989.0, "n_streams_by_mode": {"FULL": 0, "LITE": 6, "SKIP": 0, "OFFLOAD": 0}}, "t_collect": 1773604612.6055863}, "action": null, "n_active": 6, "mode_counts": {"FULL": 0, "LITE": 6, "SKIP": 0, "OFFLOAD": 0}}, {"step": 39, "t_elapsed": 40.28, "events": [], "observation": {"per_stream": {"0": {"fps_avg": 14.3, "infer_fps": 14.3, "latency_p95_ms": 100.89, "infer_latency_p95_ms": 100.89, "current_mode": "LITE", "detection_count_avg": 1.56, "frames_in_current_mode": 14, "frame_count": 14}, "1": {"fps_avg": 14.31, "infer_fps": 14.31, "latency_p95_ms": 119.54, "infer_latency_p95_ms": 119.54, "current_mode": "LITE", "detection_count_avg": 1.71, "frames_in_current_mode": 14, "frame_count": 14}, "2": {"fps_avg": 13.26, "infer_fps": 13.26, "latency_p95_ms": 118.26, "infer_latency_p95_ms": 118.26, "current_mode": "LITE", "detection_count_avg": 1.25, "frames_in_current_mode": 13, "frame_count": 13}, "3": {"fps_avg": 13.26, "infer_fps": 13.26, "latency_p95_ms": 124.41, "infer_latency_p95_ms": 124.41, "current_mode": "LITE", "detection_count_avg": 4.54, "frames_in_current_mode": 13, "frame_count": 13}, "4": {"fps_avg": 13.23, "infer_fps": 13.23, "latency_p95_ms": 119.55, "infer_latency_p95_ms": 119.55, "current_mode": "LITE", "detection_count_avg": 1.83, "frames_in_current_mode": 13, "frame_count": 13}, "5": {"fps_avg": 13.21, "infer_fps": 13.21, "latency_p95_ms": 121.55, "infer_latency_p95_ms": 121.55, "current_mode": "LITE", "detection_count_avg": 6.38, "frames_in_current_mode": 13, "frame_count": 13}}, "global": {"gpu_util_avg": 32.0, "n_active_streams": 6, "mem_used_mb": 5989.0, "n_streams_by_mode": {"FULL": 0, "LITE": 6, "SKIP": 0, "OFFLOAD": 0}}, "t_collect": 1773604613.6141434}, "action": null, "n_active": 6, "mode_counts": {"FULL": 0, "LITE": 6, "SKIP": 0, "OFFLOAD": 0}}, {"step": 40, "t_elapsed": 41.29, "events": ["add_stream"], "observation": {"per_stream": {"0": {"fps_avg": 12.34, "infer_fps": 12.34, "latency_p95_ms": 102.75, "infer_latency_p95_ms": 102.75, "current_mode": "LITE", "detection_count_avg": 1.64, "frames_in_current_mode": 11, "frame_count": 11}, "1": {"fps_avg": 12.4, "infer_fps": 12.4, "latency_p95_ms": 101.39, "infer_latency_p95_ms": 101.39, "current_mode": "LITE", "detection_count_avg": 2.0, "frames_in_current_mode": 11, "frame_count": 11}, "2": {"fps_avg": 12.4, "infer_fps": 12.4, "latency_p95_ms": 98.7, "infer_latency_p95_ms": 98.7, "current_mode": "LITE", "detection_count_avg": 1.82, "frames_in_current_mode": 11, "frame_count": 11}, "3": {"fps_avg": 12.33, "infer_fps": 12.33, "latency_p95_ms": 105.64, "infer_latency_p95_ms": 105.64, "current_mode": "LITE", "detection_count_avg": 3.0, "frames_in_current_mode": 11, "frame_count": 11}, "4": {"fps_avg": 12.25, "infer_fps": 12.25, "latency_p95_ms": 103.5, "infer_latency_p95_ms": 103.5, "current_mode": "LITE", "detection_count_avg": 2.36, "frames_in_current_mode": 11, "frame_count": 11}, "5": {"fps_avg": 12.37, "infer_fps": 12.37, "latency_p95_ms": 97.85, "infer_latency_p95_ms": 97.85, "current_mode": "LITE", "detection_count_avg": 6.27, "frames_in_current_mode": 11, "frame_count": 11}, "6": {"fps_avg": 17.17, "infer_fps": 17.17, "latency_p95_ms": 87.7, "infer_latency_p95_ms": 87.7, "current_mode": "FULL", "detection_count_avg": 6.07, "frames_in_current_mode": 14, "frame_count": 14}}, "global": {"gpu_util_avg": 54.7, "n_active_streams": 7, "mem_used_mb": 6011.0, "n_streams_by_mode": {"FULL": 1, "LITE": 6, "SKIP": 0, "OFFLOAD": 0}}, "t_collect": 1773604614.6254463}, "action": null, "n_active": 7, "mode_counts": {"FULL": 1, "LITE": 6, "SKIP": 0, "OFFLOAD": 0}}, {"step": 41, "t_elapsed": 42.29, "events": [], "observation": {"per_stream": {"0": {"fps_avg": 12.15, "infer_fps": 12.15, "latency_p95_ms": 121.4, "infer_latency_p95_ms": 121.4, "current_mode": "LITE", "detection_count_avg": 2.0, "frames_in_current_mode": 11, "frame_count": 11}, "1": {"fps_avg": 13.29, "infer_fps": 13.29, "latency_p95_ms": 93.62, "infer_latency_p95_ms": 93.62, "current_mode": "LITE", "detection_count_avg": 2.42, "frames_in_current_mode": 12, "frame_count": 12}, "2": {"fps_avg": 13.26, "infer_fps": 13.26, "latency_p95_ms": 90.27, "infer_latency_p95_ms": 90.27, "current_mode": "LITE", "detection_count_avg": 2.0, "frames_in_current_mode": 12, "frame_count": 12}, "3": {"fps_avg": 11.98, "infer_fps": 11.98, "latency_p95_ms": 126.12, "infer_latency_p95_ms": 126.12, "current_mode": "LITE", "detection_count_avg": 2.9, "frames_in_current_mode": 10, "frame_count": 10}, "4": {"fps_avg": 13.27, "infer_fps": 13.27, "latency_p95_ms": 91.39, "infer_latency_p95_ms": 91.39, "current_mode": "LITE", "detection_count_avg": 2.0, "frames_in_current_mode": 11, "frame_count": 11}, "5": {"fps_avg": 12.11, "infer_fps": 12.11, "latency_p95_ms": 124.52, "infer_latency_p95_ms": 124.52, "current_mode": "LITE", "detection_count_avg": 5.45, "frames_in_current_mode": 11, "frame_count": 11}, "6": {"fps_avg": 19.78, "infer_fps": 19.78, "latency_p95_ms": 73.49, "infer_latency_p95_ms": 73.49, "current_mode": "FULL", "detection_count_avg": 6.95, "frames_in_current_mode": 19, "frame_count": 19}}, "global": {"gpu_util_avg": 39.2, "n_active_streams": 7, "mem_used_mb": 6015.0, "n_streams_by_mode": {"FULL": 1, "LITE": 6, "SKIP": 0, "OFFLOAD": 0}}, "t_collect": 1773604615.634368}, "action": {"stream_id": 6, "from_mode": "FULL", "to_mode": "LITE", "dwell_was": 1}, "n_active": 7, "mode_counts": {"FULL": 1, "LITE": 6, "SKIP": 0, "OFFLOAD": 0}}, {"step": 42, "t_elapsed": 43.32, "events": [], "observation": {"per_stream": {"0": {"fps_avg": 10.91, "infer_fps": 10.91, "latency_p95_ms": 180.02, "infer_latency_p95_ms": 180.02, "current_mode": "LITE", "detection_count_avg": 2.0, "frames_in_current_mode": 10, "frame_count": 10}, "1": {"fps_avg": 9.57, "infer_fps": 9.57, "latency_p95_ms": 204.38, "infer_latency_p95_ms": 204.38, "current_mode": "LITE", "detection_count_avg": 2.78, "frames_in_current_mode": 9, "frame_count": 9}, "2": {"fps_avg": 11.71, "infer_fps": 11.71, "latency_p95_ms": 187.13, "infer_latency_p95_ms": 187.13, "current_mode": "LITE", "detection_count_avg": 2.45, "frames_in_current_mode": 11, "frame_count": 11}, "3": {"fps_avg": 10.07, "infer_fps": 10.07, "latency_p95_ms": 180.66, "infer_latency_p95_ms": 180.66, "current_mode": "LITE", "detection_count_avg": 3.2, "frames_in_current_mode": 10, "frame_count": 10}, "4": {"fps_avg": 9.06, "infer_fps": 9.06, "latency_p95_ms": 209.03, "infer_latency_p95_ms": 209.03, "current_mode": "LITE", "detection_count_avg": 2.0, "frames_in_current_mode": 9, "frame_count": 9}, "5": {"fps_avg": 12.76, "infer_fps": 12.76, "latency_p95_ms": 179.29, "infer_latency_p95_ms": 179.29, "current_mode": "LITE", "detection_count_avg": 4.42, "frames_in_current_mode": 12, "frame_count": 12}, "6": {"fps_avg": 10.1, "infer_fps": 10.1, "latency_p95_ms": 194.49, "infer_latency_p95_ms": 194.49, "current_mode": "LITE", "detection_count_avg": 6.2, "frames_in_current_mode": 10, "frame_count": 10}}, "global": {"gpu_util_avg": 65.0, "n_active_streams": 7, "mem_used_mb": 6017.0, "n_streams_by_mode": {"FULL": 0, "LITE": 7, "SKIP": 0, "OFFLOAD": 0}}, "t_collect": 1773604616.6467354}, "action": null, "n_active": 7, "mode_counts": {"FULL": 0, "LITE": 7, "SKIP": 0, "OFFLOAD": 0}}, {"step": 43, "t_elapsed": 44.33, "events": [], "observation": {"per_stream": {"0": {"fps_avg": 11.65, "infer_fps": 11.65, "latency_p95_ms": 133.18, "infer_latency_p95_ms": 133.18, "current_mode": "LITE", "detection_count_avg": 2.82, "frames_in_current_mode": 11, "frame_count": 11}, "1": {"fps_avg": 11.57, "infer_fps": 11.57, "latency_p95_ms": 132.0, "infer_latency_p95_ms": 132.0, "current_mode": "LITE", "detection_count_avg": 2.2, "frames_in_current_mode": 10, "frame_count": 10}, "2": {"fps_avg": 13.88, "infer_fps": 13.88, "latency_p95_ms": 109.64, "infer_latency_p95_ms": 109.64, "current_mode": "LITE", "detection_count_avg": 2.5, "frames_in_current_mode": 12, "frame_count": 12}, "3": {"fps_avg": 11.61, "infer_fps": 11.61, "latency_p95_ms": 134.13, "infer_latency_p95_ms": 134.13, "current_mode": "LITE", "detection_count_avg": 1.8, "frames_in_current_mode": 10, "frame_count": 10}, "4": {"fps_avg": 12.72, "infer_fps": 12.72, "latency_p95_ms": 124.11, "infer_latency_p95_ms": 124.11, "current_mode": "LITE", "detection_count_avg": 3.0, "frames_in_current_mode": 11, "frame_count": 11}, "5": {"fps_avg": 12.86, "infer_fps": 12.86, "latency_p95_ms": 122.95, "infer_latency_p95_ms": 122.95, "current_mode": "LITE", "detection_count_avg": 5.0, "frames_in_current_mode": 11, "frame_count": 11}, "6": {"fps_avg": 13.44, "infer_fps": 13.44, "latency_p95_ms": 136.82, "infer_latency_p95_ms": 136.82, "current_mode": "LITE", "detection_count_avg": 5.82, "frames_in_current_mode": 11, "frame_count": 11}}, "global": {"gpu_util_avg": 51.7, "n_active_streams": 7, "mem_used_mb": 6018.0, "n_streams_by_mode": {"FULL": 0, "LITE": 7, "SKIP": 0, "OFFLOAD": 0}}, "t_collect": 1773604617.669508}, "action": null, "n_active": 7, "mode_counts": {"FULL": 0, "LITE": 7, "SKIP": 0, "OFFLOAD": 0}}, {"step": 44, "t_elapsed": 45.34, "events": [], "observation": {"per_stream": {"0": {"fps_avg": 13.61, "infer_fps": 13.61, "latency_p95_ms": 108.84, "infer_latency_p95_ms": 108.84, "current_mode": "LITE", "detection_count_avg": 2.31, "frames_in_current_mode": 13, "frame_count": 13}, "1": {"fps_avg": 12.27, "infer_fps": 12.27, "latency_p95_ms": 118.48, "infer_latency_p95_ms": 118.48, "current_mode": "LITE", "detection_count_avg": 1.45, "frames_in_current_mode": 11, "frame_count": 11}, "2": {"fps_avg": 12.48, "infer_fps": 12.48, "latency_p95_ms": 118.09, "infer_latency_p95_ms": 118.09, "current_mode": "LITE", "detection_count_avg": 2.08, "frames_in_current_mode": 12, "frame_count": 12}, "3": {"fps_avg": 13.44, "infer_fps": 13.44, "latency_p95_ms": 107.95, "infer_latency_p95_ms": 107.95, "current_mode": "LITE", "detection_count_avg": 2.0, "frames_in_current_mode": 12, "frame_count": 12}, "4": {"fps_avg": 12.48, "infer_fps": 12.48, "latency_p95_ms": 123.39, "infer_latency_p95_ms": 123.39, "current_mode": "LITE", "detection_count_avg": 3.17, "frames_in_current_mode": 12, "frame_count": 12}, "5": {"fps_avg": 13.59, "infer_fps": 13.59, "latency_p95_ms": 111.28, "infer_latency_p95_ms": 111.28, "current_mode": "LITE", "detection_count_avg": 3.54, "frames_in_current_mode": 13, "frame_count": 13}, "6": {"fps_avg": 11.44, "infer_fps": 11.44, "latency_p95_ms": 124.88, "infer_latency_p95_ms": 124.88, "current_mode": "LITE", "detection_count_avg": 4.36, "frames_in_current_mode": 11, "frame_count": 11}}, "global": {"gpu_util_avg": 47.7, "n_active_streams": 7, "mem_used_mb": 6018.0, "n_streams_by_mode": {"FULL": 0, "LITE": 7, "SKIP": 0, "OFFLOAD": 0}}, "t_collect": 1773604618.6786945}, "action": null, "n_active": 7, "mode_counts": {"FULL": 0, "LITE": 7, "SKIP": 0, "OFFLOAD": 0}}, {"step": 45, "t_elapsed": 46.35, "events": [], "observation": {"per_stream": {"0": {"fps_avg": 11.87, "infer_fps": 11.87, "latency_p95_ms": 118.12, "infer_latency_p95_ms": 118.12, "current_mode": "LITE", "detection_count_avg": 1.45, "frames_in_current_mode": 11, "frame_count": 11}, "1": {"fps_avg": 12.91, "infer_fps": 12.91, "latency_p95_ms": 124.72, "infer_latency_p95_ms": 124.72, "current_mode": "LITE", "detection_count_avg": 2.75, "frames_in_current_mode": 12, "frame_count": 12}, "2": {"fps_avg": 12.75, "infer_fps": 12.75, "latency_p95_ms": 123.23, "infer_latency_p95_ms": 123.23, "current_mode": "LITE", "detection_count_avg": 1.91, "frames_in_current_mode": 11, "frame_count": 11}, "3": {"fps_avg": 12.94, "infer_fps": 12.94, "latency_p95_ms": 124.76, "infer_latency_p95_ms": 124.76, "current_mode": "LITE", "detection_count_avg": 2.17, "frames_in_current_mode": 12, "frame_count": 12}, "4": {"fps_avg": 12.76, "infer_fps": 12.76, "latency_p95_ms": 125.87, "infer_latency_p95_ms": 125.87, "current_mode": "LITE", "detection_count_avg": 3.36, "frames_in_current_mode": 11, "frame_count": 11}, "5": {"fps_avg": 11.83, "infer_fps": 11.83, "latency_p95_ms": 120.44, "infer_latency_p95_ms": 120.44, "current_mode": "LITE", "detection_count_avg": 3.0, "frames_in_current_mode": 11, "frame_count": 11}, "6": {"fps_avg": 11.57, "infer_fps": 11.57, "latency_p95_ms": 125.85, "infer_latency_p95_ms": 125.85, "current_mode": "LITE", "detection_count_avg": 4.0, "frames_in_current_mode": 10, "frame_count": 10}}, "global": {"gpu_util_avg": 81.5, "n_active_streams": 7, "mem_used_mb": 6018.0, "n_streams_by_mode": {"FULL": 0, "LITE": 7, "SKIP": 0, "OFFLOAD": 0}}, "t_collect": 1773604619.6865678}, "action": null, "n_active": 7, "mode_counts": {"FULL": 0, "LITE": 7, "SKIP": 0, "OFFLOAD": 0}}, {"step": 46, "t_elapsed": 47.37, "events": [], "observation": {"per_stream": {"0": {"fps_avg": 13.4, "infer_fps": 13.4, "latency_p95_ms": 106.81, "infer_latency_p95_ms": 106.81, "current_mode": "LITE", "detection_count_avg": 2.58, "frames_in_current_mode": 12, "frame_count": 12}, "1": {"fps_avg": 12.24, "infer_fps": 12.24, "latency_p95_ms": 135.92, "infer_latency_p95_ms": 135.92, "current_mode": "LITE", "detection_count_avg": 4.4, "frames_in_current_mode": 10, "frame_count": 10}, "2": {"fps_avg": 11.59, "infer_fps": 11.59, "latency_p95_ms": 140.18, "infer_latency_p95_ms": 140.18, "current_mode": "LITE", "detection_count_avg": 3.1, "frames_in_current_mode": 10, "frame_count": 10}, "3": {"fps_avg": 11.64, "infer_fps": 11.64, "latency_p95_ms": 134.52, "infer_latency_p95_ms": 134.52, "current_mode": "LITE", "detection_count_avg": 2.0, "frames_in_current_mode": 11, "frame_count": 11}, "4": {"fps_avg": 13.47, "infer_fps": 13.47, "latency_p95_ms": 135.65, "infer_latency_p95_ms": 135.65, "current_mode": "LITE", "detection_count_avg": 4.0, "frames_in_current_mode": 11, "frame_count": 11}, "5": {"fps_avg": 12.28, "infer_fps": 12.28, "latency_p95_ms": 132.04, "infer_latency_p95_ms": 132.04, "current_mode": "LITE", "detection_count_avg": 4.27, "frames_in_current_mode": 11, "frame_count": 11}, "6": {"fps_avg": 12.13, "infer_fps": 12.13, "latency_p95_ms": 142.63, "infer_latency_p95_ms": 142.63, "current_mode": "LITE", "detection_count_avg": 3.6, "frames_in_current_mode": 10, "frame_count": 10}}, "global": {"gpu_util_avg": 53.5, "n_active_streams": 7, "mem_used_mb": 6019.0, "n_streams_by_mode": {"FULL": 0, "LITE": 7, "SKIP": 0, "OFFLOAD": 0}}, "t_collect": 1773604620.710731}, "action": null, "n_active": 7, "mode_counts": {"FULL": 0, "LITE": 7, "SKIP": 0, "OFFLOAD": 0}}, {"step": 47, "t_elapsed": 48.39, "events": [], "observation": {"per_stream": {"0": {"fps_avg": 12.29, "infer_fps": 12.29, "latency_p95_ms": 134.5, "infer_latency_p95_ms": 134.5, "current_mode": "LITE", "detection_count_avg": 4.58, "frames_in_current_mode": 12, "frame_count": 12}, "1": {"fps_avg": 12.4, "infer_fps": 12.4, "latency_p95_ms": 135.06, "infer_latency_p95_ms": 135.06, "current_mode": "LITE", "detection_count_avg": 6.45, "frames_in_current_mode": 11, "frame_count": 11}, "2": {"fps_avg": 12.33, "infer_fps": 12.33, "latency_p95_ms": 116.37, "infer_latency_p95_ms": 116.37, "current_mode": "LITE", "detection_count_avg": 5.42, "frames_in_current_mode": 12, "frame_count": 12}, "3": {"fps_avg": 12.38, "infer_fps": 12.38, "latency_p95_ms": 107.55, "infer_latency_p95_ms": 107.55, "current_mode": "LITE", "detection_count_avg": 2.58, "frames_in_current_mode": 12, "frame_count": 12}, "4": {"fps_avg": 12.38, "infer_fps": 12.38, "latency_p95_ms": 134.85, "infer_latency_p95_ms": 134.85, "current_mode": "LITE", "detection_count_avg": 5.17, "frames_in_current_mode": 12, "frame_count": 12}, "5": {"fps_avg": 13.33, "infer_fps": 13.33, "latency_p95_ms": 112.63, "infer_latency_p95_ms": 112.63, "current_mode": "LITE", "detection_count_avg": 2.62, "frames_in_current_mode": 13, "frame_count": 13}, "6": {"fps_avg": 12.38, "infer_fps": 12.38, "latency_p95_ms": 129.33, "infer_latency_p95_ms": 129.33, "current_mode": "LITE", "detection_count_avg": 4.83, "frames_in_current_mode": 12, "frame_count": 12}}, "global": {"gpu_util_avg": 15.5, "n_active_streams": 7, "mem_used_mb": 6018.0, "n_streams_by_mode": {"FULL": 0, "LITE": 7, "SKIP": 0, "OFFLOAD": 0}}, "t_collect": 1773604621.7216482}, "action": null, "n_active": 7, "mode_counts": {"FULL": 0, "LITE": 7, "SKIP": 0, "OFFLOAD": 0}}, {"step": 48, "t_elapsed": 49.4, "events": [], "observation": {"per_stream": {"0": {"fps_avg": 12.52, "infer_fps": 12.52, "latency_p95_ms": 113.48, "infer_latency_p95_ms": 113.48, "current_mode": "LITE", "detection_count_avg": 6.27, "frames_in_current_mode": 11, "frame_count": 11}, "1": {"fps_avg": 12.67, "infer_fps": 12.67, "latency_p95_ms": 111.8, "infer_latency_p95_ms": 111.8, "current_mode": "LITE", "detection_count_avg": 4.75, "frames_in_current_mode": 12, "frame_count": 12}, "2": {"fps_avg": 12.52, "infer_fps": 12.52, "latency_p95_ms": 123.87, "infer_latency_p95_ms": 123.87, "current_mode": "LITE", "detection_count_avg": 5.45, "frames_in_current_mode": 11, "frame_count": 11}, "3": {"fps_avg": 12.45, "infer_fps": 12.45, "latency_p95_ms": 123.27, "infer_latency_p95_ms": 123.27, "current_mode": "LITE", "detection_count_avg": 2.0, "frames_in_current_mode": 11, "frame_count": 11}, "4": {"fps_avg": 13.87, "infer_fps": 13.87, "latency_p95_ms": 108.12, "infer_latency_p95_ms": 108.12, "current_mode": "LITE", "detection_count_avg": 5.58, "frames_in_current_mode": 12, "frame_count": 12}, "5": {"fps_avg": 13.67, "infer_fps": 13.67, "latency_p95_ms": 106.14, "infer_latency_p95_ms": 106.14, "current_mode": "LITE", "detection_count_avg": 1.0, "frames_in_current_mode": 12, "frame_count": 12}, "6": {"fps_avg": 12.53, "infer_fps": 12.53, "latency_p95_ms": 117.86, "infer_latency_p95_ms": 117.86, "current_mode": "LITE", "detection_count_avg": 5.18, "frames_in_current_mode": 11, "frame_count": 11}}, "global": {"gpu_util_avg": 9.7, "n_active_streams": 7, "mem_used_mb": 6018.0, "n_streams_by_mode": {"FULL": 0, "LITE": 7, "SKIP": 0, "OFFLOAD": 0}}, "t_collect": 1773604622.738658}, "action": null, "n_active": 7, "mode_counts": {"FULL": 0, "LITE": 7, "SKIP": 0, "OFFLOAD": 0}}, {"step": 49, "t_elapsed": 50.41, "events": [], "observation": {"per_stream": {"0": {"fps_avg": 12.24, "infer_fps": 12.24, "latency_p95_ms": 121.42, "infer_latency_p95_ms": 121.42, "current_mode": "LITE", "detection_count_avg": 4.73, "frames_in_current_mode": 11, "frame_count": 11}, "1": {"fps_avg": 12.08, "infer_fps": 12.08, "latency_p95_ms": 126.62, "infer_latency_p95_ms": 126.62, "current_mode": "LITE", "detection_count_avg": 4.09, "frames_in_current_mode": 11, "frame_count": 11}, "2": {"fps_avg": 14.52, "infer_fps": 14.52, "latency_p95_ms": 88.48, "infer_latency_p95_ms": 88.48, "current_mode": "LITE", "detection_count_avg": 4.57, "frames_in_current_mode": 14, "frame_count": 14}, "3": {"fps_avg": 12.49, "infer_fps": 12.49, "latency_p95_ms": 123.59, "infer_latency_p95_ms": 123.59, "current_mode": "LITE", "detection_count_avg": 3.0, "frames_in_current_mode": 12, "frame_count": 12}, "4": {"fps_avg": 12.16, "infer_fps": 12.16, "latency_p95_ms": 125.22, "infer_latency_p95_ms": 125.22, "current_mode": "LITE", "detection_count_avg": 4.45, "frames_in_current_mode": 11, "frame_count": 11}, "5": {"fps_avg": 12.09, "infer_fps": 12.09, "latency_p95_ms": 120.04, "infer_latency_p95_ms": 120.04, "current_mode": "LITE", "detection_count_avg": 1.44, "frames_in_current_mode": 11, "frame_count": 11}, "6": {"fps_avg": 12.45, "infer_fps": 12.45, "latency_p95_ms": 125.22, "infer_latency_p95_ms": 125.22, "current_mode": "LITE", "detection_count_avg": 5.92, "frames_in_current_mode": 12, "frame_count": 12}}, "global": {"gpu_util_avg": 50.6, "n_active_streams": 7, "mem_used_mb": 6017.0, "n_streams_by_mode": {"FULL": 0, "LITE": 7, "SKIP": 0, "OFFLOAD": 0}}, "t_collect": 1773604623.7452426}, "action": null, "n_active": 7, "mode_counts": {"FULL": 0, "LITE": 7, "SKIP": 0, "OFFLOAD": 0}}, {"step": 50, "t_elapsed": 51.42, "events": [], "observation": {"per_stream": {"0": {"fps_avg": 11.61, "infer_fps": 11.61, "latency_p95_ms": 127.37, "infer_latency_p95_ms": 127.37, "current_mode": "LITE", "detection_count_avg": 4.1, "frames_in_current_mode": 10, "frame_count": 10}, "1": {"fps_avg": 12.09, "infer_fps": 12.09, "latency_p95_ms": 125.65, "infer_latency_p95_ms": 125.65, "current_mode": "LITE", "detection_count_avg": 3.27, "frames_in_current_mode": 11, "frame_count": 11}, "2": {"fps_avg": 14.42, "infer_fps": 14.42, "latency_p95_ms": 98.92, "infer_latency_p95_ms": 98.92, "current_mode": "LITE", "detection_count_avg": 3.54, "frames_in_current_mode": 13, "frame_count": 13}, "3": {"fps_avg": 11.65, "infer_fps": 11.65, "latency_p95_ms": 129.36, "infer_latency_p95_ms": 129.36, "current_mode": "LITE", "detection_count_avg": 2.4, "frames_in_current_mode": 10, "frame_count": 10}, "4": {"fps_avg": 12.78, "infer_fps": 12.78, "latency_p95_ms": 130.3, "infer_latency_p95_ms": 130.3, "current_mode": "LITE", "detection_count_avg": 7.0, "frames_in_current_mode": 11, "frame_count": 11}, "5": {"fps_avg": 11.65, "infer_fps": 11.65, "latency_p95_ms": 130.99, "infer_latency_p95_ms": 130.99, "current_mode": "LITE", "detection_count_avg": 2.1, "frames_in_current_mode": 10, "frame_count": 10}, "6": {"fps_avg": 14.01, "infer_fps": 14.01, "latency_p95_ms": 104.47, "infer_latency_p95_ms": 104.47, "current_mode": "LITE", "detection_count_avg": 6.92, "frames_in_current_mode": 12, "frame_count": 12}}, "global": {"gpu_util_avg": 57.9, "n_active_streams": 7, "mem_used_mb": 6017.0, "n_streams_by_mode": {"FULL": 0, "LITE": 7, "SKIP": 0, "OFFLOAD": 0}}, "t_collect": 1773604624.757921}, "action": null, "n_active": 7, "mode_counts": {"FULL": 0, "LITE": 7, "SKIP": 0, "OFFLOAD": 0}}, {"step": 51, "t_elapsed": 52.44, "events": [], "observation": {"per_stream": {"0": {"fps_avg": 12.24, "infer_fps": 12.24, "latency_p95_ms": 121.01, "infer_latency_p95_ms": 121.01, "current_mode": "LITE", "detection_count_avg": 3.33, "frames_in_current_mode": 12, "frame_count": 12}, "1": {"fps_avg": 12.34, "infer_fps": 12.34, "latency_p95_ms": 114.92, "infer_latency_p95_ms": 114.92, "current_mode": "LITE", "detection_count_avg": 2.75, "frames_in_current_mode": 12, "frame_count": 12}, "2": {"fps_avg": 13.36, "infer_fps": 13.36, "latency_p95_ms": 103.17, "infer_latency_p95_ms": 103.17, "current_mode": "LITE", "detection_count_avg": 2.85, "frames_in_current_mode": 13, "frame_count": 13}, "3": {"fps_avg": 13.2, "infer_fps": 13.2, "latency_p95_ms": 120.99, "infer_latency_p95_ms": 120.99, "current_mode": "LITE", "detection_count_avg": 1.56, "frames_in_current_mode": 13, "frame_count": 13}, "4": {"fps_avg": 12.11, "infer_fps": 12.11, "latency_p95_ms": 126.09, "infer_latency_p95_ms": 126.09, "current_mode": "LITE", "detection_count_avg": 6.42, "frames_in_current_mode": 12, "frame_count": 12}, "5": {"fps_avg": 12.24, "infer_fps": 12.24, "latency_p95_ms": 122.13, "infer_latency_p95_ms": 122.13, "current_mode": "LITE", "detection_count_avg": 2.25, "frames_in_current_mode": 12, "frame_count": 12}, "6": {"fps_avg": 12.25, "infer_fps": 12.25, "latency_p95_ms": 120.63, "infer_latency_p95_ms": 120.63, "current_mode": "LITE", "detection_count_avg": 6.25, "frames_in_current_mode": 12, "frame_count": 12}}, "global": {"gpu_util_avg": 55.5, "n_active_streams": 7, "mem_used_mb": 6017.0, "n_streams_by_mode": {"FULL": 0, "LITE": 7, "SKIP": 0, "OFFLOAD": 0}}, "t_collect": 1773604625.772967}, "action": null, "n_active": 7, "mode_counts": {"FULL": 0, "LITE": 7, "SKIP": 0, "OFFLOAD": 0}}, {"step": 52, "t_elapsed": 53.47, "events": [], "observation": {"per_stream": {"0": {"fps_avg": 11.82, "infer_fps": 11.82, "latency_p95_ms": 126.89, "infer_latency_p95_ms": 126.89, "current_mode": "LITE", "detection_count_avg": 2.82, "frames_in_current_mode": 11, "frame_count": 11}, "1": {"fps_avg": 13.01, "infer_fps": 13.01, "latency_p95_ms": 114.28, "infer_latency_p95_ms": 114.28, "current_mode": "LITE", "detection_count_avg": 1.64, "frames_in_current_mode": 11, "frame_count": 11}, "2": {"fps_avg": 12.7, "infer_fps": 12.7, "latency_p95_ms": 110.1, "infer_latency_p95_ms": 110.1, "current_mode": "LITE", "detection_count_avg": 1.67, "frames_in_current_mode": 12, "frame_count": 12}, "3": {"fps_avg": 11.85, "infer_fps": 11.85, "latency_p95_ms": 127.8, "infer_latency_p95_ms": 127.8, "current_mode": "LITE", "detection_count_avg": 1.5, "frames_in_current_mode": 11, "frame_count": 11}, "4": {"fps_avg": 11.84, "infer_fps": 11.84, "latency_p95_ms": 129.96, "infer_latency_p95_ms": 129.96, "current_mode": "LITE", "detection_count_avg": 7.18, "frames_in_current_mode": 11, "frame_count": 11}, "5": {"fps_avg": 12.87, "infer_fps": 12.87, "latency_p95_ms": 111.82, "infer_latency_p95_ms": 111.82, "current_mode": "LITE", "detection_count_avg": 2.0, "frames_in_current_mode": 12, "frame_count": 12}, "6": {"fps_avg": 12.9, "infer_fps": 12.9, "latency_p95_ms": 112.86, "infer_latency_p95_ms": 112.86, "current_mode": "LITE", "detection_count_avg": 5.75, "frames_in_current_mode": 12, "frame_count": 12}}, "global": {"gpu_util_avg": 38.5, "n_active_streams": 7, "mem_used_mb": 6017.0, "n_streams_by_mode": {"FULL": 0, "LITE": 7, "SKIP": 0, "OFFLOAD": 0}}, "t_collect": 1773604626.7988648}, "action": null, "n_active": 7, "mode_counts": {"FULL": 0, "LITE": 7, "SKIP": 0, "OFFLOAD": 0}}, {"step": 53, "t_elapsed": 54.5, "events": [], "observation": {"per_stream": {"0": {"fps_avg": 13.02, "infer_fps": 13.02, "latency_p95_ms": 100.47, "infer_latency_p95_ms": 100.47, "current_mode": "LITE", "detection_count_avg": 1.64, "frames_in_current_mode": 11, "frame_count": 11}, "1": {"fps_avg": 12.9, "infer_fps": 12.9, "latency_p95_ms": 105.48, "infer_latency_p95_ms": 105.48, "current_mode": "LITE", "detection_count_avg": 2.92, "frames_in_current_mode": 13, "frame_count": 13}, "2": {"fps_avg": 14.17, "infer_fps": 14.17, "latency_p95_ms": 89.39, "infer_latency_p95_ms": 89.39, "current_mode": "LITE", "detection_count_avg": 2.92, "frames_in_current_mode": 13, "frame_count": 13}, "3": {"fps_avg": 13.02, "infer_fps": 13.02, "latency_p95_ms": 108.06, "infer_latency_p95_ms": 108.06, "current_mode": "LITE", "detection_count_avg": 2.08, "frames_in_current_mode": 12, "frame_count": 12}, "4": {"fps_avg": 12.85, "infer_fps": 12.85, "latency_p95_ms": 108.16, "infer_latency_p95_ms": 108.16, "current_mode": "LITE", "detection_count_avg": 6.08, "frames_in_current_mode": 12, "frame_count": 12}, "5": {"fps_avg": 12.84, "infer_fps": 12.84, "latency_p95_ms": 107.98, "infer_latency_p95_ms": 107.98, "current_mode": "LITE", "detection_count_avg": 2.58, "frames_in_current_mode": 12, "frame_count": 12}, "6": {"fps_avg": 13.04, "infer_fps": 13.04, "latency_p95_ms": 109.91, "infer_latency_p95_ms": 109.91, "current_mode": "LITE", "detection_count_avg": 5.58, "frames_in_current_mode": 12, "frame_count": 12}}, "global": {"gpu_util_avg": 46.3, "n_active_streams": 7, "mem_used_mb": 6017.0, "n_streams_by_mode": {"FULL": 0, "LITE": 7, "SKIP": 0, "OFFLOAD": 0}}, "t_collect": 1773604627.8253002}, "action": null, "n_active": 7, "mode_counts": {"FULL": 0, "LITE": 7, "SKIP": 0, "OFFLOAD": 0}}, {"step": 54, "t_elapsed": 55.51, "events": [], "observation": {"per_stream": {"0": {"fps_avg": 11.78, "infer_fps": 11.78, "latency_p95_ms": 128.02, "infer_latency_p95_ms": 128.02, "current_mode": "LITE", "detection_count_avg": 2.73, "frames_in_current_mode": 11, "frame_count": 11}, "1": {"fps_avg": 11.05, "infer_fps": 11.05, "latency_p95_ms": 137.93, "infer_latency_p95_ms": 137.93, "current_mode": "LITE", "detection_count_avg": 4.78, "frames_in_current_mode": 9, "frame_count": 9}, "2": {"fps_avg": 11.49, "infer_fps": 11.49, "latency_p95_ms": 132.18, "infer_latency_p95_ms": 132.18, "current_mode": "LITE", "detection_count_avg": 4.8, "frames_in_current_mode": 10, "frame_count": 10}, "3": {"fps_avg": 12.63, "infer_fps": 12.63, "latency_p95_ms": 122.25, "infer_latency_p95_ms": 122.25, "current_mode": "LITE", "detection_count_avg": 2.0, "frames_in_current_mode": 11, "frame_count": 11}, "4": {"fps_avg": 12.6, "infer_fps": 12.6, "latency_p95_ms": 129.48, "infer_latency_p95_ms": 129.48, "current_mode": "LITE", "detection_count_avg": 4.64, "frames_in_current_mode": 11, "frame_count": 11}, "5": {"fps_avg": 11.05, "infer_fps": 11.05, "latency_p95_ms": 128.55, "infer_latency_p95_ms": 128.55, "current_mode": "LITE", "detection_count_avg": 3.33, "frames_in_current_mode": 9, "frame_count": 9}, "6": {"fps_avg": 11.44, "infer_fps": 11.44, "latency_p95_ms": 126.56, "infer_latency_p95_ms": 126.56, "current_mode": "LITE", "detection_count_avg": 4.0, "frames_in_current_mode": 10, "frame_count": 10}}, "global": {"gpu_util_avg": 43.6, "n_active_streams": 7, "mem_used_mb": 6016.0, "n_streams_by_mode": {"FULL": 0, "LITE": 7, "SKIP": 0, "OFFLOAD": 0}}, "t_collect": 1773604628.8457754}, "action": null, "n_active": 7, "mode_counts": {"FULL": 0, "LITE": 7, "SKIP": 0, "OFFLOAD": 0}}, {"step": 55, "t_elapsed": 56.51, "events": [], "observation": {"per_stream": {"0": {"fps_avg": 11.71, "infer_fps": 11.71, "latency_p95_ms": 128.29, "infer_latency_p95_ms": 128.29, "current_mode": "LITE", "detection_count_avg": 4.45, "frames_in_current_mode": 11, "frame_count": 11}, "1": {"fps_avg": 11.47, "infer_fps": 11.47, "latency_p95_ms": 131.72, "infer_latency_p95_ms": 131.72, "current_mode": "LITE", "detection_count_avg": 3.91, "frames_in_current_mode": 11, "frame_count": 11}, "2": {"fps_avg": 11.73, "infer_fps": 11.73, "latency_p95_ms": 128.63, "infer_latency_p95_ms": 128.63, "current_mode": "LITE", "detection_count_avg": 3.73, "frames_in_current_mode": 11, "frame_count": 11}, "3": {"fps_avg": 11.65, "infer_fps": 11.65, "latency_p95_ms": 127.9, "infer_latency_p95_ms": 127.9, "current_mode": "LITE", "detection_count_avg": 2.91, "frames_in_current_mode": 11, "frame_count": 11}, "4": {"fps_avg": 13.64, "infer_fps": 13.64, "latency_p95_ms": 130.12, "infer_latency_p95_ms": 130.12, "current_mode": "LITE", "detection_count_avg": 3.08, "frames_in_current_mode": 13, "frame_count": 13}, "5": {"fps_avg": 10.59, "infer_fps": 10.59, "latency_p95_ms": 133.36, "infer_latency_p95_ms": 133.36, "current_mode": "LITE", "detection_count_avg": 2.8, "frames_in_current_mode": 10, "frame_count": 10}, "6": {"fps_avg": 12.78, "infer_fps": 12.78, "latency_p95_ms": 125.4, "infer_latency_p95_ms": 125.4, "current_mode": "LITE", "detection_count_avg": 4.42, "frames_in_current_mode": 12, "frame_count": 12}}, "global": {"gpu_util_avg": 68.7, "n_active_streams": 7, "mem_used_mb": 6016.0, "n_streams_by_mode": {"FULL": 0, "LITE": 7, "SKIP": 0, "OFFLOAD": 0}}, "t_collect": 1773604629.8546147}, "action": null, "n_active": 7, "mode_counts": {"FULL": 0, "LITE": 7, "SKIP": 0, "OFFLOAD": 0}}, {"step": 56, "t_elapsed": 57.52, "events": [], "observation": {"per_stream": {"0": {"fps_avg": 12.97, "infer_fps": 12.97, "latency_p95_ms": 123.06, "infer_latency_p95_ms": 123.06, "current_mode": "LITE", "detection_count_avg": 3.92, "frames_in_current_mode": 12, "frame_count": 12}, "1": {"fps_avg": 11.87, "infer_fps": 11.87, "latency_p95_ms": 128.05, "infer_latency_p95_ms": 128.05, "current_mode": "LITE", "detection_count_avg": 2.55, "frames_in_current_mode": 11, "frame_count": 11}, "2": {"fps_avg": 11.64, "infer_fps": 11.64, "latency_p95_ms": 132.28, "infer_latency_p95_ms": 132.28, "current_mode": "LITE", "detection_count_avg": 2.45, "frames_in_current_mode": 11, "frame_count": 11}, "3": {"fps_avg": 13.99, "infer_fps": 13.99, "latency_p95_ms": 102.92, "infer_latency_p95_ms": 102.92, "current_mode": "LITE", "detection_count_avg": 2.23, "frames_in_current_mode": 13, "frame_count": 13}, "4": {"fps_avg": 11.9, "infer_fps": 11.9, "latency_p95_ms": 121.74, "infer_latency_p95_ms": 121.74, "current_mode": "LITE", "detection_count_avg": 3.0, "frames_in_current_mode": 11, "frame_count": 11}, "5": {"fps_avg": 12.92, "infer_fps": 12.92, "latency_p95_ms": 126.14, "infer_latency_p95_ms": 126.14, "current_mode": "LITE", "detection_count_avg": 4.0, "frames_in_current_mode": 12, "frame_count": 12}, "6": {"fps_avg": 11.85, "infer_fps": 11.85, "latency_p95_ms": 127.04, "infer_latency_p95_ms": 127.04, "current_mode": "LITE", "detection_count_avg": 3.36, "frames_in_current_mode": 11, "frame_count": 11}}, "global": {"gpu_util_avg": 32.2, "n_active_streams": 7, "mem_used_mb": 6016.0, "n_streams_by_mode": {"FULL": 0, "LITE": 7, "SKIP": 0, "OFFLOAD": 0}}, "t_collect": 1773604630.8612485}, "action": null, "n_active": 7, "mode_counts": {"FULL": 0, "LITE": 7, "SKIP": 0, "OFFLOAD": 0}}, {"step": 57, "t_elapsed": 58.53, "events": [], "observation": {"per_stream": {"0": {"fps_avg": 12.63, "infer_fps": 12.63, "latency_p95_ms": 118.55, "infer_latency_p95_ms": 118.55, "current_mode": "LITE", "detection_count_avg": 2.55, "frames_in_current_mode": 11, "frame_count": 11}, "1": {"fps_avg": 12.96, "infer_fps": 12.96, "latency_p95_ms": 116.59, "infer_latency_p95_ms": 116.59, "current_mode": "LITE", "detection_count_avg": 3.08, "frames_in_current_mode": 12, "frame_count": 12}, "2": {"fps_avg": 12.8, "infer_fps": 12.8, "latency_p95_ms": 110.25, "infer_latency_p95_ms": 110.25, "current_mode": "LITE", "detection_count_avg": 3.18, "frames_in_current_mode": 11, "frame_count": 11}, "3": {"fps_avg": 12.58, "infer_fps": 12.58, "latency_p95_ms": 112.42, "infer_latency_p95_ms": 112.42, "current_mode": "LITE", "detection_count_avg": 1.45, "frames_in_current_mode": 11, "frame_count": 11}, "4": {"fps_avg": 11.58, "infer_fps": 11.58, "latency_p95_ms": 134.08, "infer_latency_p95_ms": 134.08, "current_mode": "LITE", "detection_count_avg": 3.1, "frames_in_current_mode": 10, "frame_count": 10}, "5": {"fps_avg": 11.94, "infer_fps": 11.94, "latency_p95_ms": 134.35, "infer_latency_p95_ms": 134.35, "current_mode": "LITE", "detection_count_avg": 3.91, "frames_in_current_mode": 11, "frame_count": 11}, "6": {"fps_avg": 13.77, "infer_fps": 13.77, "latency_p95_ms": 98.71, "infer_latency_p95_ms": 98.71, "current_mode": "LITE", "detection_count_avg": 3.58, "frames_in_current_mode": 12, "frame_count": 12}}, "global": {"gpu_util_avg": 35.2, "n_active_streams": 7, "mem_used_mb": 6016.0, "n_streams_by_mode": {"FULL": 0, "LITE": 7, "SKIP": 0, "OFFLOAD": 0}}, "t_collect": 1773604631.8707411}, "action": null, "n_active": 7, "mode_counts": {"FULL": 0, "LITE": 7, "SKIP": 0, "OFFLOAD": 0}}, {"step": 58, "t_elapsed": 59.54, "events": [], "observation": {"per_stream": {"0": {"fps_avg": 13.76, "infer_fps": 13.76, "latency_p95_ms": 130.37, "infer_latency_p95_ms": 130.37, "current_mode": "LITE", "detection_count_avg": 3.08, "frames_in_current_mode": 13, "frame_count": 13}, "1": {"fps_avg": 12.23, "infer_fps": 12.23, "latency_p95_ms": 110.78, "infer_latency_p95_ms": 110.78, "current_mode": "LITE", "detection_count_avg": 5.0, "frames_in_current_mode": 11, "frame_count": 11}, "2": {"fps_avg": 13.69, "infer_fps": 13.69, "latency_p95_ms": 117.71, "infer_latency_p95_ms": 117.71, "current_mode": "LITE", "detection_count_avg": 4.92, "frames_in_current_mode": 13, "frame_count": 13}, "3": {"fps_avg": 13.29, "infer_fps": 13.29, "latency_p95_ms": 125.69, "infer_latency_p95_ms": 125.69, "current_mode": "LITE", "detection_count_avg": 2.75, "frames_in_current_mode": 12, "frame_count": 12}, "4": {"fps_avg": 13.29, "infer_fps": 13.29, "latency_p95_ms": 126.51, "infer_latency_p95_ms": 126.51, "current_mode": "LITE", "detection_count_avg": 1.67, "frames_in_current_mode": 12, "frame_count": 12}, "5": {"fps_avg": 12.29, "infer_fps": 12.29, "latency_p95_ms": 113.33, "infer_latency_p95_ms": 113.33, "current_mode": "LITE", "detection_count_avg": 6.0, "frames_in_current_mode": 11, "frame_count": 11}, "6": {"fps_avg": 12.19, "infer_fps": 12.19, "latency_p95_ms": 127.5, "infer_latency_p95_ms": 127.5, "current_mode": "LITE", "detection_count_avg": 3.64, "frames_in_current_mode": 11, "frame_count": 11}}, "global": {"gpu_util_avg": 50.6, "n_active_streams": 7, "mem_used_mb": 6016.0, "n_streams_by_mode": {"FULL": 0, "LITE": 7, "SKIP": 0, "OFFLOAD": 0}}, "t_collect": 1773604632.881808}, "action": null, "n_active": 7, "mode_counts": {"FULL": 0, "LITE": 7, "SKIP": 0, "OFFLOAD": 0}}, {"step": 59, "t_elapsed": 60.55, "events": [], "observation": {"per_stream": {"0": {"fps_avg": 12.52, "infer_fps": 12.52, "latency_p95_ms": 117.23, "infer_latency_p95_ms": 117.23, "current_mode": "LITE", "detection_count_avg": 5.18, "frames_in_current_mode": 11, "frame_count": 11}, "1": {"fps_avg": 11.39, "infer_fps": 11.39, "latency_p95_ms": 123.3, "infer_latency_p95_ms": 123.3, "current_mode": "LITE", "detection_count_avg": 5.3, "frames_in_current_mode": 10, "frame_count": 10}, "2": {"fps_avg": 11.44, "infer_fps": 11.44, "latency_p95_ms": 135.08, "infer_latency_p95_ms": 135.08, "current_mode": "LITE", "detection_count_avg": 5.7, "frames_in_current_mode": 10, "frame_count": 10}, "3": {"fps_avg": 12.47, "infer_fps": 12.47, "latency_p95_ms": 129.38, "infer_latency_p95_ms": 129.38, "current_mode": "LITE", "detection_count_avg": 4.64, "frames_in_current_mode": 11, "frame_count": 11}, "4": {"fps_avg": 12.42, "infer_fps": 12.42, "latency_p95_ms": 123.68, "infer_latency_p95_ms": 123.68, "current_mode": "LITE", "detection_count_avg": 2.09, "frames_in_current_mode": 11, "frame_count": 11}, "5": {"fps_avg": 11.44, "infer_fps": 11.44, "latency_p95_ms": 128.65, "infer_latency_p95_ms": 128.65, "current_mode": "LITE", "detection_count_avg": 5.3, "frames_in_current_mode": 10, "frame_count": 10}, "6": {"fps_avg": 12.52, "infer_fps": 12.52, "latency_p95_ms": 129.75, "infer_latency_p95_ms": 129.75, "current_mode": "LITE", "detection_count_avg": 2.09, "frames_in_current_mode": 11, "frame_count": 11}}, "global": {"gpu_util_avg": 32.4, "n_active_streams": 7, "mem_used_mb": 6016.0, "n_streams_by_mode": {"FULL": 0, "LITE": 7, "SKIP": 0, "OFFLOAD": 0}}, "t_collect": 1773604633.8895752}, "action": null, "n_active": 7, "mode_counts": {"FULL": 0, "LITE": 7, "SKIP": 0, "OFFLOAD": 0}}]