{
  "config": {
    "n_runs": 3,
    "controllers": [
      "dqn"
    ],
    "scenarios": [
      "scenario_ramp_up",
      "scenario_burst",
      "scenario_steady_overload",
      "scenario_oscillating"
    ],
    "train_episodes": 5,
    "timestamp": "2026-03-16T11:31:18.319389"
  },
  "summaries": [
    {
      "run_id": 1,
      "controller": "dqn",
      "scenario": "scenario_ramp_up",
      "slo_satisfaction_rate": 0.9521,
      "slo_violations": 15,
      "total_windows": 313,
      "n_mode_switches": 16,
      "skip_ratio": 0.0,
      "offload_ratio": 0.1949,
      "avg_fps": 14.88,
      "avg_latency_ms": 94.03,
      "steps": 59
    },
    {
      "run_id": 1,
      "controller": "dqn",
      "scenario": "scenario_burst",
      "slo_satisfaction_rate": 0.9472,
      "slo_violations": 13,
      "total_windows": 246,
      "n_mode_switches": 3,
      "skip_ratio": 0.1689,
      "offload_ratio": 0.3818,
      "avg_fps": 14.0,
      "avg_latency_ms": 98.52,
      "steps": 59
    },
    {
      "run_id": 1,
      "controller": "dqn",
      "scenario": "scenario_steady_overload",
      "slo_satisfaction_rate": 0.9722,
      "slo_violations": 14,
      "total_windows": 503,
      "n_mode_switches": 87,
      "skip_ratio": 0.0473,
      "offload_ratio": 0.2424,
      "avg_fps": 13.75,
      "avg_latency_ms": 101.85,
      "steps": 88
    },
    {
      "run_id": 1,
      "controller": "dqn",
      "scenario": "scenario_oscillating",
      "slo_satisfaction_rate": 0.9613,
      "slo_violations": 21,
      "total_windows": 542,
      "n_mode_switches": 11,
      "skip_ratio": 0.0163,
      "offload_ratio": 0.4102,
      "avg_fps": 15.03,
      "avg_latency_ms": 92.09,
      "steps": 117
    },
    {
      "run_id": 2,
      "controller": "dqn",
      "scenario": "scenario_ramp_up",
      "slo_satisfaction_rate": 0.9617,
      "slo_violations": 12,
      "total_windows": 313,
      "n_mode_switches": 5,
      "skip_ratio": 0.0,
      "offload_ratio": 0.2939,
      "avg_fps": 14.89,
      "avg_latency_ms": 92.24,
      "steps": 59
    },
    {
      "run_id": 2,
      "controller": "dqn",
      "scenario": "scenario_burst",
      "slo_satisfaction_rate": 0.8661,
      "slo_violations": 32,
      "total_windows": 239,
      "n_mode_switches": 38,
      "skip_ratio": 0.173,
      "offload_ratio": 0.2491,
      "avg_fps": 13.91,
      "avg_latency_ms": 109.05,
      "steps": 58
    },
    {
      "run_id": 2,
      "controller": "dqn",
      "scenario": "scenario_steady_overload",
      "slo_satisfaction_rate": 0.9564,
      "slo_violations": 23,
      "total_windows": 528,
      "n_mode_switches": 13,
      "skip_ratio": 0.0,
      "offload_ratio": 0.3068,
      "avg_fps": 14.02,
      "avg_latency_ms": 94.01,
      "steps": 88
    },
    {
      "run_id": 2,
      "controller": "dqn",
      "scenario": "scenario_oscillating",
      "slo_satisfaction_rate": 0.9744,
      "slo_violations": 14,
      "total_windows": 546,
      "n_mode_switches": 10,
      "skip_ratio": 0.0091,
      "offload_ratio": 0.2069,
      "avg_fps": 16.53,
      "avg_latency_ms": 85.16,
      "steps": 117
    },
    {
      "run_id": 3,
      "controller": "dqn",
      "scenario": "scenario_ramp_up",
      "slo_satisfaction_rate": 0.9712,
      "slo_violations": 9,
      "total_windows": 313,
      "n_mode_switches": 17,
      "skip_ratio": 0.0,
      "offload_ratio": 0.1853,
      "avg_fps": 14.86,
      "avg_latency_ms": 92.45,
      "steps": 59
    },
    {
      "run_id": 3,
      "controller": "dqn",
      "scenario": "scenario_burst",
      "slo_satisfaction_rate": 0.8852,
      "slo_violations": 28,
      "total_windows": 244,
      "n_mode_switches": 15,
      "skip_ratio": 0.1557,
      "offload_ratio": 0.2837,
      "avg_fps": 13.59,
      "avg_latency_ms": 107.58,
      "steps": 58
    },
    {
      "run_id": 3,
      "controller": "dqn",
      "scenario": "scenario_steady_overload",
      "slo_satisfaction_rate": 0.9435,
      "slo_violations": 27,
      "total_windows": 478,
      "n_mode_switches": 77,
      "skip_ratio": 0.0947,
      "offload_ratio": 0.1723,
      "avg_fps": 14.9,
      "avg_latency_ms": 99.03,
      "steps": 88
    },
    {
      "run_id": 3,
      "controller": "dqn",
      "scenario": "scenario_oscillating",
      "slo_satisfaction_rate": 0.9596,
      "slo_violations": 22,
      "total_windows": 545,
      "n_mode_switches": 116,
      "skip_ratio": 0.0109,
      "offload_ratio": 0.0962,
      "avg_fps": 16.49,
      "avg_latency_ms": 87.2,
      "steps": 117
    }
  ]
}